{
  ":version":                  "6.9.10 f.LUM",
  "file_hash":                 ["Mask of Truth", "Deku Stick", "Master Sword", "Frog", "Mask of Truth"],
  ":seed":                     "LMA0EE6CW7-88",
  ":settings_string":          "BSA4BGBSWJAA34CBAEAJLEASJCAECKAEAAABAJAAAEACSSAAAC2ALSFWBA3RYEGKL3V8YZELVAFAJAASAESHFEABE6KACDCSAAJJHNLB",
  ":enable_distribution_file": false,
  "settings":                  {
    "show_seed_info":                          true,
    "user_message":                            "S6 Tournament",
    "world_count":                             1,
    "create_spoiler":                          true,
    "randomize_settings":                      false,
    "logic_rules":                             "glitchless",
    "reachable_locations":                     "all",
    "triforce_hunt":                           false,
    "lacs_condition":                          "vanilla",
    "bridge":                                  "medallions",
    "bridge_medallions":                       6,
    "trials_random":                           false,
    "trials":                                  0,
    "shuffle_ganon_bosskey":                   "remove",
    "shuffle_bosskeys":                        "dungeon",
    "shuffle_smallkeys":                       "dungeon",
    "shuffle_hideoutkeys":                     "vanilla",
    "key_rings_choice":                        "off",
    "shuffle_mapcompass":                      "startwith",
    "enhance_map_compass":                     false,
    "open_forest":                             "closed_deku",
    "open_kakariko":                           "open",
    "open_door_of_time":                       true,
    "zora_fountain":                           "closed",
    "gerudo_fortress":                         "fast",
    "dungeon_shortcuts_choice":                "off",
    "starting_age":                            "random",
    "mq_dungeons_mode":                        "vanilla",
    "empty_dungeons_mode":                     "none",
    "shuffle_interior_entrances":              "off",
    "shuffle_grotto_entrances":                false,
    "shuffle_dungeon_entrances":               "off",
    "shuffle_bosses":                          "off",
    "shuffle_overworld_entrances":             false,
    "owl_drops":                               false,
    "warp_songs":                              false,
    "spawn_positions":                         [
      "child"
    ],
    "bombchus_in_logic":                       false,
    "one_item_per_dungeon":                    false,
    "shuffle_song_items":                      "song",
    "shopsanity":                              "off",
    "tokensanity":                             "off",
    "shuffle_scrubs":                          "off",
    "shuffle_child_trade":                     "skip_child_zelda",
    "shuffle_freestanding_items":              "off",
    "shuffle_pots":                            "off",
    "shuffle_crates":                          "off",
    "shuffle_cows":                            false,
    "shuffle_beehives":                        false,
    "shuffle_kokiri_sword":                    true,
    "shuffle_ocarinas":                        false,
    "shuffle_gerudo_card":                     false,
    "shuffle_beans":                           false,
    "shuffle_medigoron_carpet_salesman":       false,
    "shuffle_frog_song_rupees":                false,
    "logic_no_night_tokens_without_suns_song": false,
    "disabled_locations":                      [
      "Deku Theater Mask of Truth"
    ],
    "allowed_tricks":                          [
      "logic_fewer_tunic_requirements",
      "logic_grottos_without_agony",
      "logic_child_deadhand",
      "logic_man_on_roof",
      "logic_dc_jump",
      "logic_rusted_switches",
      "logic_windmill_poh",
      "logic_crater_bean_poh_with_hovers",
      "logic_forest_vines",
      "logic_lens_botw",
      "logic_lens_castle",
      "logic_lens_gtg",
      "logic_lens_shadow",
      "logic_lens_shadow_platform",
      "logic_lens_bongo",
      "logic_lens_spirit"
    ],
    "starting_items":                          {
      "Deku Shield": 1,
      "Ocarina":     1
    },
    "start_with_consumables":                  true,
    "start_with_rupees":                       false,
    "starting_hearts":                         3,
    "no_escape_sequence":                      true,
    "no_guard_stealth":                        true,
    "no_epona_race":                           true,
    "skip_some_minigame_phases":               true,
    "complete_mask_quest":                     false,
    "useful_cutscenes":                        false,
    "fast_chests":                             true,
    "free_scarecrow":                          false,
    "fast_bunny_hood":                         true,
    "plant_beans":                             false,
    "chicken_count_random":                    false,
    "chicken_count":                           4,
    "big_poe_count_random":                    false,
    "big_poe_count":                           1,
    "easier_fire_arrow_entry":                 false,
    "ocarina_songs":                           "off",
    "correct_chest_appearances":               "both",
    "minor_items_as_major_chest":              false,
    "invisible_chests":                        false,
    "correct_potcrate_appearances":            "off",
    "clearer_hints":                           true,
    "hints":                                   "always",
    "hint_dist":                               "tournament",
    "item_hints":                              [],
    "hint_dist_user":                          {},
    "misc_hints":                              [
      "altar",
      "ganondorf",
      "warp_songs"
    ],
    "text_shuffle":                            "none",
    "damage_multiplier":                       "normal",
    "deadly_bonks":                            "none",
    "no_collectible_hearts":                   false,
    "starting_tod":                            "default",
    "blue_fire_arrows":                        false,
    "fix_broken_drops":                        false,
    "item_pool_value":                         "balanced",
    "junk_ice_traps":                          "off",
    "ice_trap_appearance":                     "junk_only",
    "adult_trade_start":                       [
      "Prescription",
      "Eyeball Frog",
      "Eyedrops",
      "Claim Check"
    ]
  },
  "randomized_settings":       {
    "starting_age": "adult"
  },
  "item_pool":                 {
    "Arrows (10)":                          9,
    "Arrows (30)":                          6,
    "Arrows (5)":                           8,
    "Biggoron Sword":                       1,
    "Bolero of Fire":                       1,
    "Bomb Bag":                             3,
    "Bombchus (10)":                        3,
    "Bombchus (20)":                        1,
    "Bombchus (5)":                         1,
    "Bombs (10)":                           2,
    "Bombs (20)":                           2,
    "Bombs (5)":                            8,
    "Boomerang":                            1,
    "Bottle with Big Poe":                  1,
    "Bottle with Poe":                      1,
    "Bottle with Red Potion":               1,
    "Bow":                                  3,
    "Deku Nut Capacity":                    2,
    "Deku Nuts (10)":                       1,
    "Deku Nuts (5)":                        3,
    "Deku Seeds (30)":                      1,
    "Deku Shield":                          3,
    "Deku Stick (1)":                       3,
    "Deku Stick Capacity":                  2,
    "Dins Fire":                            1,
    "Double Defense":                       1,
    "Eponas Song":                          1,
    "Farores Wind":                         1,
    "Fire Arrows":                          1,
    "Goron Tunic":                          1,
    "Heart Container":                      8,
    "Hover Boots":                          1,
    "Hylian Shield":                        2,
    "Ice Arrows":                           1,
    "Iron Boots":                           1,
    "Kokiri Sword":                         1,
    "Lens of Truth":                        1,
    "Light Arrows":                         1,
    "Magic Meter":                          2,
    "Megaton Hammer":                       1,
    "Minuet of Forest":                     1,
    "Mirror Shield":                        1,
    "Nayrus Love":                          1,
    "Nocturne of Shadow":                   1,
    "Piece of Heart (Treasure Chest Game)": 1,
    "Piece of Heart":                       35,
    "Prelude of Light":                     1,
    "Prescription":                         1,
    "Progressive Hookshot":                 2,
    "Progressive Scale":                    2,
    "Progressive Strength Upgrade":         3,
    "Progressive Wallet":                   2,
    "Recovery Heart":                       11,
    "Requiem of Spirit":                    1,
    "Rupee (1)":                            1,
    "Rupees (20)":                          8,
    "Rupees (200)":                         6,
    "Rupees (5)":                           20,
    "Rupees (50)":                          7,
    "Rutos Letter":                         1,
    "Sarias Song":                          1,
    "Serenade of Water":                    1,
    "Slingshot":                            3,
    "Song of Storms":                       1,
    "Song of Time":                         1,
    "Stone of Agony":                       1,
    "Suns Song":                            1,
    "Zeldas Lullaby":                       1,
    "Zora Tunic":                           1
  },
  "dungeons":                  {
    "Deku Tree":              "vanilla",
    "Dodongos Cavern":        "vanilla",
    "Jabu Jabus Belly":       "vanilla",
    "Bottom of the Well":     "vanilla",
    "Ice Cavern":             "vanilla",
    "Gerudo Training Ground": "vanilla",
    "Forest Temple":          "vanilla",
    "Fire Temple":            "vanilla",
    "Water Temple":           "vanilla",
    "Spirit Temple":          "vanilla",
    "Shadow Temple":          "vanilla",
    "Ganons Castle":          "vanilla"
  },
  "empty_dungeons":            {
    "Deku Tree":        false,
    "Dodongos Cavern":  false,
    "Jabu Jabus Belly": false,
    "Forest Temple":    false,
    "Fire Temple":      false,
    "Water Temple":     false,
    "Spirit Temple":    false,
    "Shadow Temple":    false
  },
  "trials":                    {
    "Forest": "inactive",
    "Fire":   "inactive",
    "Water":  "inactive",
    "Spirit": "inactive",
    "Shadow": "inactive",
    "Light":  "inactive"
  },
  "songs":                     {},
  "entrances":                 {
    "Child Spawn -> KF Links House": "Kak Potion Shop Back"
  },
  "locations":                 {
    "Links Pocket":                                         "Spirit Medallion",
    "Queen Gohma":                                          "Zora Sapphire",
    "King Dodongo":                                         "Goron Ruby",
    "Barinade":                                             "Forest Medallion",
    "Phantom Ganon":                                        "Kokiri Emerald",
    "Volvagia":                                             "Fire Medallion",
    "Morpha":                                               "Light Medallion",
    "Bongo Bongo":                                          "Shadow Medallion",
    "Twinrova":                                             "Water Medallion",
    "Song from Impa":                                       "Requiem of Spirit",
    "Song from Malon":                                      "Bolero of Fire",
    "Song from Saria":                                      "Suns Song",
    "Song from Royal Familys Tomb":                         "Song of Storms",
    "Song from Ocarina of Time":                            "Eponas Song",
    "Song from Windmill":                                   "Prelude of Light",
    "Sheik in Forest":                                      "Sarias Song",
    "Sheik in Crater":                                      "Serenade of Water",
    "Sheik in Ice Cavern":                                  "Minuet of Forest",
    "Sheik at Colossus":                                    "Zeldas Lullaby",
    "Sheik in Kakariko":                                    "Nocturne of Shadow",
    "Sheik at Temple":                                      "Song of Time",
    "KF Midos Top Left Chest":                              "Bow",
    "KF Midos Top Right Chest":                             "Ice Arrows",
    "KF Midos Bottom Left Chest":                           "Deku Seeds (30)",
    "KF Midos Bottom Right Chest":                          "Piece of Heart",
    "KF Kokiri Sword Chest":                                "Bottle with Red Potion",
    "KF Storms Grotto Chest":                               "Rupees (5)",
    "LW Ocarina Memory Game":                               "Arrows (10)",
    "LW Target in Woods":                                   "Bombs (5)",
    "LW Near Shortcuts Grotto Chest":                       "Bombs (5)",
    "Deku Theater Skull Mask":                              "Rupees (20)",
    "Deku Theater Mask of Truth":                           "Rupees (200)",
    "LW Skull Kid":                                         "Recovery Heart",
    "LW Deku Scrub Near Bridge":                            {"item": "Rupees (200)", "price": 40},
    "LW Deku Scrub Grotto Front":                           {"item": "Heart Container", "price": 40},
    "SFM Wolfos Grotto Chest":                              "Arrows (5)",
    "HF Near Market Grotto Chest":                          "Bombs (5)",
    "HF Tektite Grotto Freestanding PoH":                   "Bombchus (10)",
    "HF Southeast Grotto Chest":                            "Rupees (5)",
    "HF Open Grotto Chest":                                 "Deku Stick (1)",
    "HF Deku Scrub Grotto":                                 {"item": "Bomb Bag", "price": 10},
    "Market Shooting Gallery Reward":                       "Piece of Heart",
    "Market Bombchu Bowling First Prize":                   "Fire Arrows",
    "Market Bombchu Bowling Second Prize":                  "Rupees (200)",
    "Market Lost Dog":                                      "Piece of Heart",
    "Market Treasure Chest Game Reward":                    "Piece of Heart",
    "Market 10 Big Poes":                                   "Deku Stick (1)",
    "ToT Light Arrows Cutscene":                            "Arrows (30)",
    "HC Great Fairy Reward":                                "Bombs (10)",
    "LLR Talons Chickens":                                  "Piece of Heart",
    "LLR Freestanding PoH":                                 "Piece of Heart",
    "Kak Anju as Child":                                    "Piece of Heart",
    "Kak Anju as Adult":                                    "Rupees (5)",
    "Kak Impas House Freestanding PoH":                     "Bottle with Poe",
    "Kak Windmill Freestanding PoH":                        "Rupees (20)",
    "Kak Man on Roof":                                      "Rupees (50)",
    "Kak Open Grotto Chest":                                "Bombchus (10)",
    "Kak Redead Grotto Chest":                              "Rupees (20)",
    "Kak Shooting Gallery Reward":                          "Piece of Heart",
    "Kak 10 Gold Skulltula Reward":                         "Arrows (10)",
    "Kak 20 Gold Skulltula Reward":                         "Bombs (20)",
    "Kak 30 Gold Skulltula Reward":                         "Bombs (5)",
    "Kak 40 Gold Skulltula Reward":                         "Rupees (5)",
    "Kak 50 Gold Skulltula Reward":                         "Iron Boots",
    "Graveyard Shield Grave Chest":                         "Nayrus Love",
    "Graveyard Heart Piece Grave Chest":                    "Bombs (5)",
    "Graveyard Royal Familys Tomb Chest":                   "Rupees (5)",
    "Graveyard Freestanding PoH":                           "Piece of Heart",
    "Graveyard Dampe Gravedigging Tour":                    "Rupees (5)",
    "Graveyard Dampe Race Hookshot Chest":                  "Arrows (10)",
    "Graveyard Dampe Race Freestanding PoH":                "Deku Stick Capacity",
    "DMT Freestanding PoH":                                 "Progressive Scale",
    "DMT Chest":                                            "Bombs (5)",
    "DMT Storms Grotto Chest":                              "Arrows (10)",
    "DMT Great Fairy Reward":                               "Rupee (1)",
    "DMT Biggoron":                                         "Arrows (30)",
    "GC Darunias Joy":                                      "Piece of Heart",
    "GC Pot Freestanding PoH":                              "Arrows (5)",
    "GC Rolling Goron as Child":                            "Piece of Heart",
    "GC Rolling Goron as Adult":                            "Arrows (5)",
    "GC Maze Left Chest":                                   "Piece of Heart",
    "GC Maze Right Chest":                                  "Rupees (20)",
    "GC Maze Center Chest":                                 "Rupees (50)",
    "DMC Volcano Freestanding PoH":                         "Rupees (5)",
    "DMC Wall Freestanding PoH":                            "Piece of Heart",
    "DMC Upper Grotto Chest":                               "Slingshot",
    "DMC Great Fairy Reward":                               "Rupees (5)",
    "ZR Open Grotto Chest":                                 "Hover Boots",
    "ZR Frogs in the Rain":                                 "Rupees (20)",
    "ZR Frogs Ocarina Game":                                "Deku Nuts (5)",
    "ZR Near Open Grotto Freestanding PoH":                 "Piece of Heart",
    "ZR Near Domain Freestanding PoH":                      "Rupees (5)",
    "ZD Diving Minigame":                                   "Piece of Heart",
    "ZD Chest":                                             "Arrows (30)",
    "ZD King Zora Thawed":                                  "Rupees (5)",
    "ZF Great Fairy Reward":                                "Progressive Strength Upgrade",
    "ZF Iceberg Freestanding PoH":                          "Rupees (5)",
    "ZF Bottom Freestanding PoH":                           "Bombchus (20)",
    "LH Underwater Item":                                   "Progressive Strength Upgrade",
    "LH Child Fishing":                                     "Arrows (5)",
    "LH Adult Fishing":                                     "Rupees (200)",
    "LH Lab Dive":                                          "Rupees (200)",
    "LH Freestanding PoH":                                  "Biggoron Sword",
    "LH Sun":                                               "Hylian Shield",
    "GV Crate Freestanding PoH":                            "Progressive Wallet",
    "GV Waterfall Freestanding PoH":                        "Rupees (20)",
    "GV Chest":                                             "Rupees (5)",
    "GF Chest":                                             "Recovery Heart",
    "GF HBA 1000 Points":                                   "Bow",
    "GF HBA 1500 Points":                                   "Prescription",
    "Wasteland Chest":                                      "Recovery Heart",
    "Colossus Great Fairy Reward":                          "Goron Tunic",
    "Colossus Freestanding PoH":                            "Bombs (10)",
    "OGC Great Fairy Reward":                               "Piece of Heart",
    "Deku Tree Map Chest":                                  "Piece of Heart",
    "Deku Tree Slingshot Room Side Chest":                  "Deku Stick Capacity",
    "Deku Tree Slingshot Chest":                            "Heart Container",
    "Deku Tree Compass Chest":                              "Bombs (5)",
    "Deku Tree Compass Room Side Chest":                    "Rupees (5)",
    "Deku Tree Basement Chest":                             "Piece of Heart",
    "Deku Tree Queen Gohma Heart":                          "Piece of Heart",
    "Dodongos Cavern Map Chest":                            "Dins Fire",
    "Dodongos Cavern Compass Chest":                        "Rupees (5)",
    "Dodongos Cavern Bomb Flower Platform Chest":           "Piece of Heart",
    "Dodongos Cavern Bomb Bag Chest":                       "Bombs (5)",
    "Dodongos Cavern End of Bridge Chest":                  "Deku Nut Capacity",
    "Dodongos Cavern Boss Room Chest":                      "Heart Container",
    "Dodongos Cavern King Dodongo Heart":                   "Arrows (5)",
    "Jabu Jabus Belly Boomerang Chest":                     "Progressive Wallet",
    "Jabu Jabus Belly Map Chest":                           "Progressive Hookshot",
    "Jabu Jabus Belly Compass Chest":                       "Rupees (5)",
    "Jabu Jabus Belly Barinade Heart":                      "Mirror Shield",
    "Bottom of the Well Front Left Fake Wall Chest":        "Small Key (Bottom of the Well)",
    "Bottom of the Well Front Center Bombable Chest":       "Piece of Heart",
    "Bottom of the Well Back Left Bombable Chest":          "Lens of Truth",
    "Bottom of the Well Underwater Left Chest":             "Rupees (5)",
    "Bottom of the Well Freestanding Key":                  "Small Key (Bottom of the Well)",
    "Bottom of the Well Compass Chest":                     "Progressive Hookshot",
    "Bottom of the Well Center Skulltula Chest":            "Deku Shield",
    "Bottom of the Well Right Bottom Fake Wall Chest":      "Small Key (Bottom of the Well)",
    "Bottom of the Well Fire Keese Chest":                  "Arrows (30)",
    "Bottom of the Well Like Like Chest":                   "Rutos Letter",
    "Bottom of the Well Map Chest":                         "Piece of Heart",
    "Bottom of the Well Underwater Front Chest":            "Arrows (10)",
    "Bottom of the Well Invisible Chest":                   "Stone of Agony",
    "Bottom of the Well Lens of Truth Chest":               "Magic Meter",
    "Forest Temple First Room Chest":                       "Piece of Heart (Treasure Chest Game)",
    "Forest Temple First Stalfos Chest":                    "Recovery Heart",
    "Forest Temple Raised Island Courtyard Chest":          "Small Key (Forest Temple)",
    "Forest Temple Map Chest":                              "Small Key (Forest Temple)",
    "Forest Temple Well Chest":                             "Small Key (Forest Temple)",
    "Forest Temple Eye Switch Chest":                       "Recovery Heart",
    "Forest Temple Boss Key Chest":                         "Rupees (20)",
    "Forest Temple Floormaster Chest":                      "Slingshot",
    "Forest Temple Red Poe Chest":                          "Boss Key (Forest Temple)",
    "Forest Temple Bow Chest":                              "Small Key (Forest Temple)",
    "Forest Temple Blue Poe Chest":                         "Small Key (Forest Temple)",
    "Forest Temple Falling Ceiling Room Chest":             "Rupees (200)",
    "Forest Temple Basement Chest":                         "Rupees (50)",
    "Forest Temple Phantom Ganon Heart":                    "Rupees (20)",
    "Fire Temple Near Boss Chest":                          "Heart Container",
    "Fire Temple Flare Dancer Chest":                       "Small Key (Fire Temple)",
    "Fire Temple Boss Key Chest":                           "Heart Container",
    "Fire Temple Big Lava Room Lower Open Door Chest":      "Small Key (Fire Temple)",
    "Fire Temple Big Lava Room Blocked Door Chest":         "Boss Key (Fire Temple)",
    "Fire Temple Boulder Maze Lower Chest":                 "Bomb Bag",
    "Fire Temple Boulder Maze Side Room Chest":             "Small Key (Fire Temple)",
    "Fire Temple Map Chest":                                "Small Key (Fire Temple)",
    "Fire Temple Boulder Maze Shortcut Chest":              "Farores Wind",
    "Fire Temple Boulder Maze Upper Chest":                 "Kokiri Sword",
    "Fire Temple Scarecrow Chest":                          "Small Key (Fire Temple)",
    "Fire Temple Compass Chest":                            "Small Key (Fire Temple)",
    "Fire Temple Megaton Hammer Chest":                     "Small Key (Fire Temple)",
    "Fire Temple Highest Goron Chest":                      "Recovery Heart",
    "Fire Temple Volvagia Heart":                           "Small Key (Fire Temple)",
    "Water Temple Compass Chest":                           "Piece of Heart",
    "Water Temple Map Chest":                               "Small Key (Water Temple)",
    "Water Temple Cracked Wall Chest":                      "Piece of Heart",
    "Water Temple Torches Chest":                           "Small Key (Water Temple)",
    "Water Temple Boss Key Chest":                          "Small Key (Water Temple)",
    "Water Temple Central Pillar Chest":                    "Small Key (Water Temple)",
    "Water Temple Central Bow Target Chest":                "Small Key (Water Temple)",
    "Water Temple Longshot Chest":                          "Piece of Heart",
    "Water Temple River Chest":                             "Boss Key (Water Temple)",
    "Water Temple Dragon Chest":                            "Small Key (Water Temple)",
    "Water Temple Morpha Heart":                            "Piece of Heart",
    "Shadow Temple Map Chest":                              "Deku Nuts (10)",
    "Shadow Temple Hover Boots Chest":                      "Rupees (50)",
    "Shadow Temple Compass Chest":                          "Small Key (Shadow Temple)",
    "Shadow Temple Early Silver Rupee Chest":               "Magic Meter",
    "Shadow Temple Invisible Blades Visible Chest":         "Slingshot",
    "Shadow Temple Invisible Blades Invisible Chest":       "Small Key (Shadow Temple)",
    "Shadow Temple Falling Spikes Lower Chest":             "Boss Key (Shadow Temple)",
    "Shadow Temple Falling Spikes Upper Chest":             "Bombchus (5)",
    "Shadow Temple Falling Spikes Switch Chest":            "Small Key (Shadow Temple)",
    "Shadow Temple Invisible Spikes Chest":                 "Piece of Heart",
    "Shadow Temple Freestanding Key":                       "Rupees (5)",
    "Shadow Temple Wind Hint Chest":                        "Small Key (Shadow Temple)",
    "Shadow Temple After Wind Enemy Chest":                 "Arrows (5)",
    "Shadow Temple After Wind Hidden Chest":                "Progressive Scale",
    "Shadow Temple Spike Walls Left Chest":                 "Arrows (10)",
    "Shadow Temple Boss Key Chest":                         "Heart Container",
    "Shadow Temple Invisible Floormaster Chest":            "Small Key (Shadow Temple)",
    "Shadow Temple Bongo Bongo Heart":                      "Arrows (10)",
    "Spirit Temple Child Bridge Chest":                     "Small Key (Spirit Temple)",
    "Spirit Temple Child Early Torches Chest":              "Recovery Heart",
    "Spirit Temple Child Climb North Chest":                "Small Key (Spirit Temple)",
    "Spirit Temple Child Climb East Chest":                 "Small Key (Spirit Temple)",
    "Spirit Temple Map Chest":                              "Recovery Heart",
    "Spirit Temple Sun Block Room Chest":                   "Deku Stick (1)",
    "Spirit Temple Silver Gauntlets Chest":                 "Bomb Bag",
    "Spirit Temple Compass Chest":                          "Bow",
    "Spirit Temple Early Adult Right Chest":                "Zora Tunic",
    "Spirit Temple First Mirror Left Chest":                "Arrows (10)",
    "Spirit Temple First Mirror Right Chest":               "Small Key (Spirit Temple)",
    "Spirit Temple Statue Room Northeast Chest":            "Boss Key (Spirit Temple)",
    "Spirit Temple Statue Room Hand Chest":                 "Piece of Heart",
    "Spirit Temple Near Four Armos Chest":                  "Small Key (Spirit Temple)",
    "Spirit Temple Hallway Right Invisible Chest":          "Rupees (5)",
    "Spirit Temple Hallway Left Invisible Chest":           "Rupees (50)",
    "Spirit Temple Mirror Shield Chest":                    "Piece of Heart",
    "Spirit Temple Boss Key Chest":                         "Piece of Heart",
    "Spirit Temple Topmost Chest":                          "Recovery Heart",
    "Spirit Temple Twinrova Heart":                         "Arrows (30)",
    "Ice Cavern Map Chest":                                 "Rupees (5)",
    "Ice Cavern Compass Chest":                             "Boomerang",
    "Ice Cavern Iron Boots Chest":                          "Rupees (50)",
    "Ice Cavern Freestanding PoH":                          "Arrows (5)",
    "Gerudo Training Ground Lobby Left Chest":              "Deku Nut Capacity",
    "Gerudo Training Ground Lobby Right Chest":             "Bottle with Big Poe",
    "Gerudo Training Ground Stalfos Chest":                 "Small Key (Gerudo Training Ground)",
    "Gerudo Training Ground Before Heavy Block Chest":      "Heart Container",
    "Gerudo Training Ground Heavy Block First Chest":       "Arrows (30)",
    "Gerudo Training Ground Heavy Block Second Chest":      "Bombchus (10)",
    "Gerudo Training Ground Heavy Block Third Chest":       "Rupees (5)",
    "Gerudo Training Ground Heavy Block Fourth Chest":      "Small Key (Gerudo Training Ground)",
    "Gerudo Training Ground Eye Statue Chest":              "Progressive Strength Upgrade",
    "Gerudo Training Ground Near Scarecrow Chest":          "Small Key (Gerudo Training Ground)",
    "Gerudo Training Ground Hammer Room Clear Chest":       "Small Key (Gerudo Training Ground)",
    "Gerudo Training Ground Hammer Room Switch Chest":      "Small Key (Gerudo Training Ground)",
    "Gerudo Training Ground Freestanding Key":              "Small Key (Gerudo Training Ground)",
    "Gerudo Training Ground Maze Right Central Chest":      "Piece of Heart",
    "Gerudo Training Ground Maze Right Side Chest":         "Piece of Heart",
    "Gerudo Training Ground Underwater Silver Rupee Chest": "Megaton Hammer",
    "Gerudo Training Ground Beamos Chest":                  "Piece of Heart",
    "Gerudo Training Ground Hidden Ceiling Chest":          "Small Key (Gerudo Training Ground)",
    "Gerudo Training Ground Maze Path First Chest":         "Deku Shield",
    "Gerudo Training Ground Maze Path Second Chest":        "Small Key (Gerudo Training Ground)",
    "Gerudo Training Ground Maze Path Third Chest":         "Small Key (Gerudo Training Ground)",
    "Gerudo Training Ground Maze Path Final Chest":         "Heart Container",
    "Ganons Castle Forest Trial Chest":                     "Hylian Shield",
    "Ganons Castle Water Trial Left Chest":                 "Small Key (Ganons Castle)",
    "Ganons Castle Water Trial Right Chest":                "Rupees (50)",
    "Ganons Castle Shadow Trial Front Chest":               "Recovery Heart",
    "Ganons Castle Shadow Trial Golden Gauntlets Chest":    "Arrows (10)",
    "Ganons Castle Light Trial First Left Chest":           "Arrows (5)",
    "Ganons Castle Light Trial Second Left Chest":          "Piece of Heart",
    "Ganons Castle Light Trial Third Left Chest":           "Piece of Heart",
    "Ganons Castle Light Trial First Right Chest":          "Bombs (20)",
    "Ganons Castle Light Trial Second Right Chest":         "Double Defense",
    "Ganons Castle Light Trial Third Right Chest":          "Small Key (Ganons Castle)",
    "Ganons Castle Light Trial Invisible Enemies Chest":    "Deku Nuts (5)",
    "Ganons Castle Light Trial Lullaby Chest":              "Deku Shield",
    "Ganons Castle Spirit Trial Crystal Switch Chest":      "Recovery Heart",
    "Ganons Castle Spirit Trial Invisible Chest":           "Deku Nuts (5)",
    "Ganons Tower Boss Key Chest":                          "Light Arrows"
  },
  ":skipped_locations":        {
    "Links Pocket":     "Spirit Medallion",
    "HC Malon Egg":     "Recovery Heart",
    "HC Zeldas Letter": "Zeldas Letter",
    "Song from Impa":   "Requiem of Spirit"
  },
  ":woth_locations":           {
    "Sheik at Colossus":                                    "Zeldas Lullaby",
    "DMT Freestanding PoH":                                 "Progressive Scale",
    "ZR Open Grotto Chest":                                 "Hover Boots",
    "Song from Royal Familys Tomb":                         "Song of Storms",
    "Dodongos Cavern Map Chest":                            "Dins Fire",
    "Bottom of the Well Lens of Truth Chest":               "Magic Meter",
    "Bottom of the Well Compass Chest":                     "Progressive Hookshot",
    "Bottom of the Well Like Like Chest":                   "Rutos Letter",
    "Ice Cavern Compass Chest":                             "Boomerang",
    "Jabu Jabus Belly Map Chest":                           "Progressive Hookshot",
    "Kak 50 Gold Skulltula Reward":                         "Iron Boots",
    "Jabu Jabus Belly Barinade Heart":                      "Mirror Shield",
    "Sheik at Temple":                                      "Song of Time",
    "Gerudo Training Ground Underwater Silver Rupee Chest": "Megaton Hammer",
    "HF Deku Scrub Grotto":                                 {"item": "Bomb Bag", "price": 10},
    "Sheik in Kakariko":                                    "Nocturne of Shadow",
    "Ganons Tower Boss Key Chest":                          "Light Arrows"
  },
  ":goal_locations":           {
    "rainbow_bridge": {
      "Path to Barinade":    {
        "Sheik at Colossus":                  "Zeldas Lullaby",
        "DMT Freestanding PoH":               "Progressive Scale",
        "Song from Royal Familys Tomb":       "Song of Storms",
        "Bottom of the Well Like Like Chest": "Rutos Letter",
        "Ice Cavern Compass Chest":           "Boomerang"
      },
      "Path to Volvagia":    {
        "Sheik at Colossus":                                    "Zeldas Lullaby",
        "DMT Freestanding PoH":                                 "Progressive Scale",
        "ZR Open Grotto Chest":                                 "Hover Boots",
        "Song from Royal Familys Tomb":                         "Song of Storms",
        "Bottom of the Well Compass Chest":                     "Progressive Hookshot",
        "Bottom of the Well Like Like Chest":                   "Rutos Letter",
        "Ice Cavern Compass Chest":                             "Boomerang",
        "Jabu Jabus Belly Map Chest":                           "Progressive Hookshot",
        "Kak 50 Gold Skulltula Reward":                         "Iron Boots",
        "Sheik at Temple":                                      "Song of Time",
        "Gerudo Training Ground Underwater Silver Rupee Chest": "Megaton Hammer",
        "HF Deku Scrub Grotto":                                 {"item": "Bomb Bag", "price": 10}
      },
      "Path to Twinrova":    {
        "Sheik at Colossus":                                    "Zeldas Lullaby",
        "DMT Freestanding PoH":                                 "Progressive Scale",
        "Song from Royal Familys Tomb":                         "Song of Storms",
        "Bottom of the Well Compass Chest":                     "Progressive Hookshot",
        "Bottom of the Well Like Like Chest":                   "Rutos Letter",
        "Ice Cavern Compass Chest":                             "Boomerang",
        "Jabu Jabus Belly Map Chest":                           "Progressive Hookshot",
        "Kak 50 Gold Skulltula Reward":                         "Iron Boots",
        "Jabu Jabus Belly Barinade Heart":                      "Mirror Shield",
        "Sheik at Temple":                                      "Song of Time",
        "Gerudo Training Ground Underwater Silver Rupee Chest": "Megaton Hammer",
        "HF Deku Scrub Grotto":                                 {"item": "Bomb Bag", "price": 10}
      },
      "Path to Bongo Bongo": {
        "Sheik at Colossus":                                    "Zeldas Lullaby",
        "DMT Freestanding PoH":                                 "Progressive Scale",
        "ZR Open Grotto Chest":                                 "Hover Boots",
        "Song from Royal Familys Tomb":                         "Song of Storms",
        "Dodongos Cavern Map Chest":                            "Dins Fire",
        "Bottom of the Well Lens of Truth Chest":               "Magic Meter",
        "Bottom of the Well Compass Chest":                     "Progressive Hookshot",
        "Bottom of the Well Like Like Chest":                   "Rutos Letter",
        "Ice Cavern Compass Chest":                             "Boomerang",
        "Jabu Jabus Belly Map Chest":                           "Progressive Hookshot",
        "Kak 50 Gold Skulltula Reward":                         "Iron Boots",
        "Jabu Jabus Belly Barinade Heart":                      "Mirror Shield",
        "Sheik at Temple":                                      "Song of Time",
        "Gerudo Training Ground Underwater Silver Rupee Chest": "Megaton Hammer",
        "HF Deku Scrub Grotto":                                 {"item": "Bomb Bag", "price": 10},
        "Sheik in Kakariko":                                    "Nocturne of Shadow"
      },
      "Path to Morpha":      {
        "Sheik at Colossus":                  "Zeldas Lullaby",
        "DMT Freestanding PoH":               "Progressive Scale",
        "Song from Royal Familys Tomb":       "Song of Storms",
        "Bottom of the Well Compass Chest":   "Progressive Hookshot",
        "Bottom of the Well Like Like Chest": "Rutos Letter",
        "Ice Cavern Compass Chest":           "Boomerang",
        "Jabu Jabus Belly Map Chest":         "Progressive Hookshot",
        "Kak 50 Gold Skulltula Reward":       "Iron Boots",
        "Sheik at Temple":                    "Song of Time"
      }
    }
  },
  ":barren_regions":           [
    "the Lost Woods",
    "the Haunted Wasteland",
    "Hyrule Castle",
    "outside Ganon's Castle",
    "Goron City",
    "Zora's Domain",
    "the Deku Tree",
    "the Water Temple"
  ],
  "gossip_stones":             {
    "Colossus (Spirit Temple)":        {"text": "They say that upon the #Colossus's left hand# is #a Piece of Heart#.", "colors": ["Green", "Red"], "hinted_locations": ["Spirit Temple Mirror Shield Chest"], "hinted_items": ["Piece of Heart"]},
    "DMC (Bombable Wall)":             {"text": "They say that #flames in the royal tomb# reveal #a Blue Rupee#.", "colors": ["Green", "Red"], "hinted_locations": ["Graveyard Royal Familys Tomb Chest"], "hinted_items": ["Rupees (5)"]},
    "DMC (Upper Grotto)":              {"text": "They say that the #Ocarina of Time# teaches #Epona's Song#.", "colors": ["Green", "Red"], "hinted_locations": ["Song from Ocarina of Time"], "hinted_items": ["Eponas Song"]},
    "DMT (Biggoron)":                  {"text": "They say that slaying #30 Gold Skulltulas# reveals #Bombs (5 pieces)#.", "colors": ["Green", "Red"], "hinted_locations": ["Kak 30 Gold Skulltula Reward"], "hinted_items": ["Bombs (5)"]},
    "DMT (Storms Grotto)":             {"text": "They say that the #treasure chest game# grants #a Piece of Heart#.", "colors": ["Green", "Red"], "hinted_locations": ["Market Treasure Chest Game Reward"], "hinted_items": ["Piece of Heart"]},
    "Dodongos Cavern (Bombable Wall)": {"text": "They say that #Jabu Jabu's Belly# is on the path to #Twinrova#.", "colors": ["Yellow", "Light Blue"], "hinted_locations": ["Jabu Jabus Belly Barinade Heart"], "hinted_items": ["Mirror Shield"]},
    "GC (Maze)":                       {"text": "They say that #Jabu Jabu's Belly# is on the path to #Twinrova#.", "colors": ["Yellow", "Light Blue"], "hinted_locations": ["Jabu Jabus Belly Barinade Heart"], "hinted_items": ["Mirror Shield"]},
    "GC (Medigoron)":                  {"text": "They say that #Biggoron# crafts #Arrows (30 pieces)#.", "colors": ["Green", "Red"], "hinted_locations": ["DMT Biggoron"], "hinted_items": ["Arrows (30)"]},
    "GV (Waterfall)":                  {"text": "They say that #the Graveyard# is on the path to #Barinade#.", "colors": ["Blue", "Light Blue"], "hinted_locations": ["Song from Royal Familys Tomb"], "hinted_items": ["Song of Storms"]},
    "Graveyard (Shadow Temple)":       {"text": "They say that a #fairy outside Ganon's Castle# holds #a Piece of Heart#.", "colors": ["Green", "Red"], "hinted_locations": ["OGC Great Fairy Reward"], "hinted_items": ["Piece of Heart"]},
    "HC (Malon)":                      {"text": "They say that #flames in the royal tomb# reveal #a Blue Rupee#.", "colors": ["Green", "Red"], "hinted_locations": ["Graveyard Royal Familys Tomb Chest"], "hinted_items": ["Rupees (5)"]},
    "HC (Rock Wall)":                  {"text": "They say that the #Skull Mask# yields #a Red Rupee#.", "colors": ["Green", "Red"], "hinted_locations": ["Deku Theater Skull Mask"], "hinted_items": ["Rupees (20)"]},
    "HC (Storms Grotto)":              {"text": "They say that upon the #Colossus's left hand# is #a Piece of Heart#.", "colors": ["Green", "Red"], "hinted_locations": ["Spirit Temple Mirror Shield Chest"], "hinted_items": ["Piece of Heart"]},
    "HF (Cow Grotto)":                 {"text": "They say that slaying #40 Gold Skulltulas# reveals #a Blue Rupee#.", "colors": ["Green", "Red"], "hinted_locations": ["Kak 40 Gold Skulltula Reward"], "hinted_items": ["Rupees (5)"]},
    "HF (Near Market Grotto)":         {"text": "They say that #Biggoron# crafts #Arrows (30 pieces)#.", "colors": ["Green", "Red"], "hinted_locations": ["DMT Biggoron"], "hinted_items": ["Arrows (30)"]},
    "HF (Open Grotto)":                {"text": "They say that shooting a #target in the woods# grants #Bombs (5 pieces)#.", "colors": ["Green", "Red"], "hinted_locations": ["LW Target in Woods"], "hinted_items": ["Bombs (5)"]},
    "HF (Southeast Grotto)":           {"text": "They say that slaying #30 Gold Skulltulas# reveals #Bombs (5 pieces)#.", "colors": ["Green", "Red"], "hinted_locations": ["Kak 30 Gold Skulltula Reward"], "hinted_items": ["Bombs (5)"]},
    "KF (Deku Tree Left)":             {"text": "They say that shooting #the sun# grants #a Hylian Shield#.", "colors": ["Green", "Red"], "hinted_locations": ["LH Sun"], "hinted_items": ["Hylian Shield"]},
    "KF (Deku Tree Right)":            {"text": "They say that #the Death Mountain Trail# is on the path to #Morpha#.", "colors": ["Blue", "Light Blue"], "hinted_locations": ["DMT Freestanding PoH"], "hinted_items": ["Progressive Scale"]},
    "KF (Outside Storms)":             {"text": "They say that a #ravaged village# mourns with #the Nocturne of Shadow#.", "colors": ["Green", "Red"], "hinted_locations": ["Sheik in Kakariko"], "hinted_items": ["Nocturne of Shadow"]},
    "KF (Storms Grotto)":              {"text": "They say that #the Death Mountain Trail# is on the path to #Morpha#.", "colors": ["Blue", "Light Blue"], "hinted_locations": ["DMT Freestanding PoH"], "hinted_items": ["Progressive Scale"]},
    "Kak (Open Grotto)":               {"text": "They say that #the Ice Cavern# is on the path to #Bongo Bongo#.", "colors": ["Pink", "Light Blue"], "hinted_locations": ["Ice Cavern Compass Chest"], "hinted_items": ["Boomerang"]},
    "LH (Lab)":                        {"text": "They say that the final reward from the #Frogs of Zora's River# is #Deku Nuts (5 pieces)#.", "colors": ["Green", "Red"], "hinted_locations": ["ZR Frogs Ocarina Game"], "hinted_items": ["Deku Nuts (5)"]},
    "LH (Southeast Corner)":           {"text": "They say that the #Ocarina of Time# teaches #Epona's Song#.", "colors": ["Green", "Red"], "hinted_locations": ["Song from Ocarina of Time"], "hinted_items": ["Eponas Song"]},
    "LH (Southwest Corner)":           {"text": "They say that #the Ice Cavern# is on the path to #Bongo Bongo#.", "colors": ["Pink", "Light Blue"], "hinted_locations": ["Ice Cavern Compass Chest"], "hinted_items": ["Boomerang"]},
    "LW (Bridge)":                     {"text": "They say that shooting a #target in the woods# grants #Bombs (5 pieces)#.", "colors": ["Green", "Red"], "hinted_locations": ["LW Target in Woods"], "hinted_items": ["Bombs (5)"]},
    "LW (Near Shortcuts Grotto)":      {"text": "They say that a school of #stingers swallowed by Jabu Jabu# guard #a Wallet#.", "colors": ["Green", "Red"], "hinted_locations": ["Jabu Jabus Belly Boomerang Chest"], "hinted_items": ["Progressive Wallet"]},
    "SFM (Maze Lower)":                {"text": "They say that the #treasure chest game# grants #a Piece of Heart#.", "colors": ["Green", "Red"], "hinted_locations": ["Market Treasure Chest Game Reward"], "hinted_items": ["Piece of Heart"]},
    "SFM (Maze Upper)":                {"text": "They say that slaying #40 Gold Skulltulas# reveals #a Blue Rupee#.", "colors": ["Green", "Red"], "hinted_locations": ["Kak 40 Gold Skulltula Reward"], "hinted_items": ["Rupees (5)"]},
    "SFM (Saria)":                     {"text": "They say that shooting #the sun# grants #a Hylian Shield#.", "colors": ["Green", "Red"], "hinted_locations": ["LH Sun"], "hinted_items": ["Hylian Shield"]},
    "ToT (Left)":                      {"text": "They say that the #Skull Mask# yields #a Red Rupee#.", "colors": ["Green", "Red"], "hinted_locations": ["Deku Theater Skull Mask"], "hinted_items": ["Rupees (20)"]},
    "ToT (Left-Center)":               {"text": "They say that a #ravaged village# mourns with #the Nocturne of Shadow#.", "colors": ["Green", "Red"], "hinted_locations": ["Sheik in Kakariko"], "hinted_items": ["Nocturne of Shadow"]},
    "ToT (Right)":                     {"text": "They say that a #fairy outside Ganon's Castle# holds #a Piece of Heart#.", "colors": ["Green", "Red"], "hinted_locations": ["OGC Great Fairy Reward"], "hinted_items": ["Piece of Heart"]},
    "ToT (Right-Center)":              {"text": "They say that #the Graveyard# is on the path to #Barinade#.", "colors": ["Blue", "Light Blue"], "hinted_locations": ["Song from Royal Familys Tomb"], "hinted_items": ["Song of Storms"]},
    "ZD (Mweep)":                      {"text": "They say that #Zora's River# is on the path to #Volvagia#.", "colors": ["Red", "Light Blue"], "hinted_locations": ["ZR Open Grotto Chest"], "hinted_items": ["Hover Boots"]},
    "ZF (Fairy)":                      {"text": "They say that slaying #50 Gold Skulltulas# reveals #the Iron Boots#.", "colors": ["Green", "Red"], "hinted_locations": ["Kak 50 Gold Skulltula Reward"], "hinted_items": ["Iron Boots"]},
    "ZF (Jabu)":                       {"text": "They say that the final reward from the #Frogs of Zora's River# is #Deku Nuts (5 pieces)#.", "colors": ["Green", "Red"], "hinted_locations": ["ZR Frogs Ocarina Game"], "hinted_items": ["Deku Nuts (5)"]},
    "ZR (Near Domain)":                {"text": "They say that #Zora's River# is on the path to #Volvagia#.", "colors": ["Red", "Light Blue"], "hinted_locations": ["ZR Open Grotto Chest"], "hinted_items": ["Hover Boots"]},
    "ZR (Near Grottos)":               {"text": "They say that a school of #stingers swallowed by Jabu Jabu# guard #a Wallet#.", "colors": ["Green", "Red"], "hinted_locations": ["Jabu Jabus Belly Boomerang Chest"], "hinted_items": ["Progressive Wallet"]},
    "ZR (Open Grotto)":                {"text": "They say that slaying #50 Gold Skulltulas# reveals #the Iron Boots#.", "colors": ["Green", "Red"], "hinted_locations": ["Kak 50 Gold Skulltula Reward"], "hinted_items": ["Iron Boots"]}
  },
  ":playthrough":              {
    "0":  {
      "HC Zeldas Letter":                                   "Zeldas Letter",
      "Links Pocket":                                       "Spirit Medallion",
      "Song from Impa":                                     "Requiem of Spirit"
    },
    "1":  {
      "DMT Freestanding PoH":                               "Progressive Scale",
      "GC GS Center Platform":                              "Gold Skulltula Token",
      "KF Midos Top Left Chest":                            "Bow",
      "Kak Bazaar Item 7":                                  "Buy Deku Stick (1)",
      "Master Sword Pedestal":                              "Time Travel",
      "OGC GS":                                             "Gold Skulltula Token",
      "Sheik at Colossus":                                  "Zeldas Lullaby",
      "ZR Open Grotto Chest":                               "Hover Boots"
    },
    "2":  {
      "GV Crate Freestanding PoH":                          "Progressive Wallet",
      "HC GS Tree":                                         "Gold Skulltula Token",
      "KF GS Know It All House":                            "Gold Skulltula Token",
      "Kak GS House Under Construction":                    "Gold Skulltula Token",
      "Kak GS Near Gate Guard":                             "Gold Skulltula Token",
      "Kak GS Skulltula House":                             "Gold Skulltula Token",
      "Kak GS Tree":                                        "Gold Skulltula Token",
      "LH GS Small Island":                                 "Gold Skulltula Token",
      "LH Underwater Item":                                 "Progressive Strength Upgrade",
      "LLR GS Rain Shed":                                   "Gold Skulltula Token",
      "LLR GS Tree":                                        "Gold Skulltula Token",
      "Market GS Guard House":                              "Gold Skulltula Token",
      "Song from Malon":                                    "Bolero of Fire",
      "Song from Royal Familys Tomb":                       "Song of Storms",
      "ZD GS Frozen Waterfall":                             "Gold Skulltula Token",
      "ZR GS Ladder":                                       "Gold Skulltula Token",
      "ZR GS Tree":                                         "Gold Skulltula Token"
    },
    "3":  {
      "Bottom of the Well Compass Chest":                   "Progressive Hookshot",
      "Bottom of the Well Freestanding Key":                "Small Key (Bottom of the Well)",
      "Bottom of the Well Front Left Fake Wall Chest":      "Small Key (Bottom of the Well)",
      "Bottom of the Well Lens of Truth Chest":             "Magic Meter",
      "Bottom of the Well Right Bottom Fake Wall Chest":    "Small Key (Bottom of the Well)",
      "Dodongos Cavern GS Side Room Near Lower Lizalfos":   "Gold Skulltula Token",
      "Dodongos Cavern GS Vines Above Stairs":              "Gold Skulltula Token",
      "Dodongos Cavern Map Chest":                          "Dins Fire",
      "GC Shop Item 5":                                     "Buy Goron Tunic"
    },
    "4":  {
      "Bottom of the Well Like Like Chest":                 "Rutos Letter",
      "Colossus GS Tree":                                   "Gold Skulltula Token",
      "Dodongos Cavern GS Alcove Above Stairs":             "Gold Skulltula Token",
      "KF GS House of Twins":                               "Gold Skulltula Token",
      "Kak GS Above Impas House":                           "Gold Skulltula Token",
      "ZR GS Above Bridge":                                 "Gold Skulltula Token",
      "ZR GS Near Raised Grottos":                          "Gold Skulltula Token"
    },
    "5":  {
      "Deliver Rutos Letter":                               "Deliver Letter"
    },
    "6":  {
      "Ice Cavern GS Spinning Scythe Room":                 "Gold Skulltula Token",
      "Ice Cavern Map Room Blue Fire":                      "Blue Fire",
      "ZF GS Tree":                                         "Gold Skulltula Token",
      "ZR Open Grotto Bug Shrub":                           "Bugs",
      "ZR Open Grotto Lone Fish":                           "Fish"
    },
    "7":  {
      "Colossus GS Bean Patch":                             "Gold Skulltula Token",
      "DMC GS Bean Patch":                                  "Gold Skulltula Token",
      "DMT GS Bean Patch":                                  "Gold Skulltula Token",
      "GV GS Bean Patch":                                   "Gold Skulltula Token",
      "Graveyard GS Bean Patch":                            "Gold Skulltula Token",
      "Ice Cavern Compass Chest":                           "Boomerang",
      "Ice Cavern GS Heart Piece Room":                     "Gold Skulltula Token",
      "Ice Cavern GS Push Block Room":                      "Gold Skulltula Token",
      "KF GS Bean Patch":                                   "Gold Skulltula Token",
      "LH GS Bean Patch":                                   "Gold Skulltula Token",
      "LW GS Bean Patch Near Bridge":                       "Gold Skulltula Token",
      "LW GS Bean Patch Near Theater":                      "Gold Skulltula Token",
      "Sheik in Ice Cavern":                                "Minuet of Forest"
    },
    "8":  {
      "Barinade":                                           "Forest Medallion",
      "Bottom of the Well GS East Inner Room":              "Gold Skulltula Token",
      "Bottom of the Well GS Like Like Cage":               "Gold Skulltula Token",
      "Bottom of the Well GS West Inner Room":              "Gold Skulltula Token",
      "Forest Temple GS First Room":                        "Gold Skulltula Token",
      "Forest Temple GS Lobby":                             "Gold Skulltula Token",
      "Forest Temple GS Raised Island Courtyard":           "Gold Skulltula Token",
      "Jabu Jabus Belly Barinade Heart":                    "Mirror Shield",
      "Jabu Jabus Belly Boomerang Chest":                   "Progressive Wallet",
      "Jabu Jabus Belly GS Lobby Basement Lower":           "Gold Skulltula Token",
      "Jabu Jabus Belly GS Lobby Basement Upper":           "Gold Skulltula Token",
      "Jabu Jabus Belly GS Water Switch Room":              "Gold Skulltula Token",
      "Jabu Jabus Belly Map Chest":                         "Progressive Hookshot",
      "LLR GS Back Wall":                                   "Gold Skulltula Token",
      "LLR GS House Window":                                "Gold Skulltula Token",
      "Spirit Temple Child Bridge Chest":                   "Small Key (Spirit Temple)",
      "Spirit Temple GS Metal Fence":                       "Gold Skulltula Token"
    },
    "9":  {
      "Colossus GS Hill":                                   "Gold Skulltula Token",
      "Dodongos Cavern GS Scarecrow":                       "Gold Skulltula Token",
      "Hideout 1 Torch Jail Gerudo Key":                    "Small Key (Thieves Hideout)",
      "Sheik at Temple":                                    "Song of Time",
      "Spirit Temple Child Climb East Chest":               "Small Key (Spirit Temple)",
      "Spirit Temple Child Climb North Chest":              "Small Key (Spirit Temple)",
      "ZD Shop Item 1":                                     "Buy Zora Tunic"
    },
    "10": {
      "Hideout Gerudo Membership Card":                     "Gerudo Membership Card",
      "Kak 50 Gold Skulltula Reward":                       "Iron Boots"
    },
    "11": {
      "Gerudo Training Ground Eye Statue Chest":            "Progressive Strength Upgrade",
      "Gerudo Training Ground Underwater Silver Rupee Chest":"Megaton Hammer",
      "Water Temple Central Bow Target Chest":              "Small Key (Water Temple)",
      "Water Temple Central Pillar Chest":                  "Small Key (Water Temple)",
      "Water Temple Dragon Chest":                          "Small Key (Water Temple)",
      "Water Temple Map Chest":                             "Small Key (Water Temple)",
      "Water Temple Torches Chest":                         "Small Key (Water Temple)"
    },
    "12": {
      "Fire Temple Flare Dancer Chest":                     "Small Key (Fire Temple)",
      "HF Deku Scrub Grotto":                               "Bomb Bag",
      "Spirit Temple First Mirror Right Chest":             "Small Key (Spirit Temple)",
      "Spirit Temple Statue Room Northeast Chest":          "Boss Key (Spirit Temple)",
      "Water Temple River Chest":                           "Boss Key (Water Temple)"
    },
    "13": {
      "Fire Temple Big Lava Room Blocked Door Chest":       "Boss Key (Fire Temple)",
      "Morpha":                                             "Light Medallion",
      "Spirit Temple Near Four Armos Chest":                "Small Key (Spirit Temple)"
    },
    "14": {
      "Twinrova":                                           "Water Medallion",
      "Volvagia":                                           "Fire Medallion"
    },
    "15": {
      "Sheik in Kakariko":                                  "Nocturne of Shadow"
    },
    "16": {
      "Shadow Temple Compass Chest":                        "Small Key (Shadow Temple)"
    },
    "17": {
      "Shadow Temple Falling Spikes Lower Chest":           "Boss Key (Shadow Temple)",
      "Shadow Temple Falling Spikes Switch Chest":          "Small Key (Shadow Temple)",
      "Shadow Temple Invisible Blades Invisible Chest":     "Small Key (Shadow Temple)"
    },
    "18": {
      "Shadow Temple Wind Hint Chest":                      "Small Key (Shadow Temple)"
    },
    "19": {
      "Shadow Temple Invisible Floormaster Chest":          "Small Key (Shadow Temple)"
    },
    "20": {
      "Bongo Bongo":                                        "Shadow Medallion"
    },
    "21": {
      "Ganons Tower Boss Key Chest":                        "Light Arrows"
    },
    "22": {
      "Ganon":                                              "Triforce"
    }
  },
  ":entrance_playthrough":     {
    "2": {
      "Child Spawn -> KF Links House":"Kak Potion Shop Back"
    }
  }
}