{
  ":version":                  "6.9.10 f.LUM",
  "file_hash":                 ["Skull Token", "Fairy Ocarina", "Megaton Hammer", "Kokiri Tunic", "Heart Container"],
  ":seed":                     "LMA0EE6CW7-91",
  ":settings_string":          "BSA4BGBSWJAA34CBAEAJLEASJCAECKAEAAABAJAAAEACSSAAAC2ALSFWBA3RYEGKL3V8YZELVAFAJAASAESHFEABE6KACDCSAAJJHNLB",
  ":enable_distribution_file": false,
  "settings":                  {
    "show_seed_info":                          true,
    "user_message":                            "S6 Tournament",
    "world_count":                             1,
    "create_spoiler":                          true,
    "randomize_settings":                      false,
    "logic_rules":                             "glitchless",
    "reachable_locations":                     "all",
    "triforce_hunt":                           false,
    "lacs_condition":                          "vanilla",
    "bridge":                                  "medallions",
    "bridge_medallions":                       6,
    "trials_random":                           false,
    "trials":                                  0,
    "shuffle_ganon_bosskey":                   "remove",
    "shuffle_bosskeys":                        "dungeon",
    "shuffle_smallkeys":                       "dungeon",
    "shuffle_hideoutkeys":                     "vanilla",
    "key_rings_choice":                        "off",
    "shuffle_mapcompass":                      "startwith",
    "enhance_map_compass":                     false,
    "open_forest":                             "closed_deku",
    "open_kakariko":                           "open",
    "open_door_of_time":                       true,
    "zora_fountain":                           "closed",
    "gerudo_fortress":                         "fast",
    "dungeon_shortcuts_choice":                "off",
    "starting_age":                            "random",
    "mq_dungeons_mode":                        "vanilla",
    "empty_dungeons_mode":                     "none",
    "shuffle_interior_entrances":              "off",
    "shuffle_grotto_entrances":                false,
    "shuffle_dungeon_entrances":               "off",
    "shuffle_bosses":                          "off",
    "shuffle_overworld_entrances":             false,
    "owl_drops":                               false,
    "warp_songs":                              false,
    "spawn_positions":                         [
      "child"
    ],
    "bombchus_in_logic":                       false,
    "one_item_per_dungeon":                    false,
    "shuffle_song_items":                      "song",
    "shopsanity":                              "off",
    "tokensanity":                             "off",
    "shuffle_scrubs":                          "off",
    "shuffle_child_trade":                     "skip_child_zelda",
    "shuffle_freestanding_items":              "off",
    "shuffle_pots":                            "off",
    "shuffle_crates":                          "off",
    "shuffle_cows":                            false,
    "shuffle_beehives":                        false,
    "shuffle_kokiri_sword":                    true,
    "shuffle_ocarinas":                        false,
    "shuffle_gerudo_card":                     false,
    "shuffle_beans":                           false,
    "shuffle_medigoron_carpet_salesman":       false,
    "shuffle_frog_song_rupees":                false,
    "logic_no_night_tokens_without_suns_song": false,
    "disabled_locations":                      [
      "Deku Theater Mask of Truth"
    ],
    "allowed_tricks":                          [
      "logic_fewer_tunic_requirements",
      "logic_grottos_without_agony",
      "logic_child_deadhand",
      "logic_man_on_roof",
      "logic_dc_jump",
      "logic_rusted_switches",
      "logic_windmill_poh",
      "logic_crater_bean_poh_with_hovers",
      "logic_forest_vines",
      "logic_lens_botw",
      "logic_lens_castle",
      "logic_lens_gtg",
      "logic_lens_shadow",
      "logic_lens_shadow_platform",
      "logic_lens_bongo",
      "logic_lens_spirit"
    ],
    "starting_items":                          {
      "Deku Shield": 1,
      "Ocarina":     1
    },
    "start_with_consumables":                  true,
    "start_with_rupees":                       false,
    "starting_hearts":                         3,
    "no_escape_sequence":                      true,
    "no_guard_stealth":                        true,
    "no_epona_race":                           true,
    "skip_some_minigame_phases":               true,
    "complete_mask_quest":                     false,
    "useful_cutscenes":                        false,
    "fast_chests":                             true,
    "free_scarecrow":                          false,
    "fast_bunny_hood":                         true,
    "plant_beans":                             false,
    "chicken_count_random":                    false,
    "chicken_count":                           4,
    "big_poe_count_random":                    false,
    "big_poe_count":                           1,
    "easier_fire_arrow_entry":                 false,
    "ocarina_songs":                           "off",
    "correct_chest_appearances":               "both",
    "minor_items_as_major_chest":              false,
    "invisible_chests":                        false,
    "correct_potcrate_appearances":            "off",
    "clearer_hints":                           true,
    "hints":                                   "always",
    "hint_dist":                               "tournament",
    "item_hints":                              [],
    "hint_dist_user":                          {},
    "misc_hints":                              [
      "altar",
      "ganondorf",
      "warp_songs"
    ],
    "text_shuffle":                            "none",
    "damage_multiplier":                       "normal",
    "deadly_bonks":                            "none",
    "no_collectible_hearts":                   false,
    "starting_tod":                            "default",
    "blue_fire_arrows":                        false,
    "fix_broken_drops":                        false,
    "item_pool_value":                         "balanced",
    "junk_ice_traps":                          "off",
    "ice_trap_appearance":                     "junk_only",
    "adult_trade_start":                       [
      "Prescription",
      "Eyeball Frog",
      "Eyedrops",
      "Claim Check"
    ]
  },
  "randomized_settings":       {
    "starting_age": "adult"
  },
  "item_pool":                 {
    "Arrows (10)":                          7,
    "Arrows (30)":                          6,
    "Arrows (5)":                           3,
    "Biggoron Sword":                       1,
    "Bolero of Fire":                       1,
    "Bomb Bag":                             3,
    "Bombchus (10)":                        3,
    "Bombchus (20)":                        1,
    "Bombchus (5)":                         1,
    "Bombs (10)":                           2,
    "Bombs (20)":                           2,
    "Bombs (5)":                            9,
    "Boomerang":                            1,
    "Bottle with Blue Fire":                1,
    "Bottle":                               2,
    "Bow":                                  3,
    "Deku Nut Capacity":                    2,
    "Deku Nuts (10)":                       1,
    "Deku Nuts (5)":                        1,
    "Deku Seeds (30)":                      7,
    "Deku Shield":                          3,
    "Deku Stick (1)":                       3,
    "Deku Stick Capacity":                  2,
    "Dins Fire":                            1,
    "Double Defense":                       1,
    "Eponas Song":                          1,
    "Eyeball Frog":                         1,
    "Farores Wind":                         1,
    "Fire Arrows":                          1,
    "Goron Tunic":                          1,
    "Heart Container":                      8,
    "Hover Boots":                          1,
    "Hylian Shield":                        2,
    "Ice Arrows":                           1,
    "Iron Boots":                           1,
    "Kokiri Sword":                         1,
    "Lens of Truth":                        1,
    "Light Arrows":                         1,
    "Magic Meter":                          2,
    "Megaton Hammer":                       1,
    "Minuet of Forest":                     1,
    "Mirror Shield":                        1,
    "Nayrus Love":                          1,
    "Nocturne of Shadow":                   1,
    "Piece of Heart (Treasure Chest Game)": 1,
    "Piece of Heart":                       35,
    "Prelude of Light":                     1,
    "Progressive Hookshot":                 2,
    "Progressive Scale":                    2,
    "Progressive Strength Upgrade":         3,
    "Progressive Wallet":                   2,
    "Recovery Heart":                       11,
    "Requiem of Spirit":                    1,
    "Rupee (1)":                            1,
    "Rupees (20)":                          6,
    "Rupees (200)":                         6,
    "Rupees (5)":                           22,
    "Rupees (50)":                          9,
    "Rutos Letter":                         1,
    "Sarias Song":                          1,
    "Serenade of Water":                    1,
    "Slingshot":                            3,
    "Song of Storms":                       1,
    "Song of Time":                         1,
    "Stone of Agony":                       1,
    "Suns Song":                            1,
    "Zeldas Lullaby":                       1,
    "Zora Tunic":                           1
  },
  "dungeons":                  {
    "Deku Tree":              "vanilla",
    "Dodongos Cavern":        "vanilla",
    "Jabu Jabus Belly":       "vanilla",
    "Bottom of the Well":     "vanilla",
    "Ice Cavern":             "vanilla",
    "Gerudo Training Ground": "vanilla",
    "Forest Temple":          "vanilla",
    "Fire Temple":            "vanilla",
    "Water Temple":           "vanilla",
    "Spirit Temple":          "vanilla",
    "Shadow Temple":          "vanilla",
    "Ganons Castle":          "vanilla"
  },
  "empty_dungeons":            {
    "Deku Tree":        false,
    "Dodongos Cavern":  false,
    "Jabu Jabus Belly": false,
    "Forest Temple":    false,
    "Fire Temple":      false,
    "Water Temple":     false,
    "Spirit Temple":    false,
    "Shadow Temple":    false
  },
  "trials":                    {
    "Forest": "inactive",
    "Fire":   "inactive",
    "Water":  "inactive",
    "Spirit": "inactive",
    "Shadow": "inactive",
    "Light":  "inactive"
  },
  "songs":                     {},
  "entrances":                 {
    "Child Spawn -> KF Links House": {"region": "Lost Woods", "from": "Kokiri Forest"}
  },
  "locations":                 {
    "Links Pocket":                                         "Fire Medallion",
    "Queen Gohma":                                          "Shadow Medallion",
    "King Dodongo":                                         "Spirit Medallion",
    "Barinade":                                             "Kokiri Emerald",
    "Phantom Ganon":                                        "Forest Medallion",
    "Volvagia":                                             "Zora Sapphire",
    "Morpha":                                               "Water Medallion",
    "Bongo Bongo":                                          "Goron Ruby",
    "Twinrova":                                             "Light Medallion",
    "Song from Impa":                                       "Sarias Song",
    "Song from Malon":                                      "Bolero of Fire",
    "Song from Saria":                                      "Minuet of Forest",
    "Song from Royal Familys Tomb":                         "Eponas Song",
    "Song from Ocarina of Time":                            "Prelude of Light",
    "Song from Windmill":                                   "Suns Song",
    "Sheik in Forest":                                      "Song of Time",
    "Sheik in Crater":                                      "Nocturne of Shadow",
    "Sheik in Ice Cavern":                                  "Serenade of Water",
    "Sheik at Colossus":                                    "Song of Storms",
    "Sheik in Kakariko":                                    "Zeldas Lullaby",
    "Sheik at Temple":                                      "Requiem of Spirit",
    "KF Midos Top Left Chest":                              "Piece of Heart",
    "KF Midos Top Right Chest":                             "Slingshot",
    "KF Midos Bottom Left Chest":                           "Double Defense",
    "KF Midos Bottom Right Chest":                          "Rupees (5)",
    "KF Kokiri Sword Chest":                                "Piece of Heart",
    "KF Storms Grotto Chest":                               "Piece of Heart",
    "LW Ocarina Memory Game":                               "Rupees (20)",
    "LW Target in Woods":                                   "Dins Fire",
    "LW Near Shortcuts Grotto Chest":                       "Megaton Hammer",
    "Deku Theater Skull Mask":                              "Rupees (200)",
    "Deku Theater Mask of Truth":                           "Bombs (10)",
    "LW Skull Kid":                                         "Recovery Heart",
    "LW Deku Scrub Near Bridge":                            {"item": "Rupees (5)", "price": 40},
    "LW Deku Scrub Grotto Front":                           {"item": "Progressive Strength Upgrade", "price": 40},
    "SFM Wolfos Grotto Chest":                              "Recovery Heart",
    "HF Near Market Grotto Chest":                          "Piece of Heart",
    "HF Tektite Grotto Freestanding PoH":                   "Bombs (5)",
    "HF Southeast Grotto Chest":                            "Hover Boots",
    "HF Open Grotto Chest":                                 "Rupees (20)",
    "HF Deku Scrub Grotto":                                 {"item": "Fire Arrows", "price": 10},
    "Market Shooting Gallery Reward":                       "Bombs (5)",
    "Market Bombchu Bowling First Prize":                   "Progressive Hookshot",
    "Market Bombchu Bowling Second Prize":                  "Piece of Heart",
    "Market Lost Dog":                                      "Rupees (20)",
    "Market Treasure Chest Game Reward":                    "Rupees (5)",
    "Market 10 Big Poes":                                   "Arrows (5)",
    "ToT Light Arrows Cutscene":                            "Recovery Heart",
    "HC Great Fairy Reward":                                "Rutos Letter",
    "LLR Talons Chickens":                                  "Rupees (5)",
    "LLR Freestanding PoH":                                 "Recovery Heart",
    "Kak Anju as Child":                                    "Piece of Heart",
    "Kak Anju as Adult":                                    "Deku Shield",
    "Kak Impas House Freestanding PoH":                     "Piece of Heart",
    "Kak Windmill Freestanding PoH":                        "Rupees (50)",
    "Kak Man on Roof":                                      "Bombs (5)",
    "Kak Open Grotto Chest":                                "Rupees (5)",
    "Kak Redead Grotto Chest":                              "Arrows (10)",
    "Kak Shooting Gallery Reward":                          "Bomb Bag",
    "Kak 10 Gold Skulltula Reward":                         "Rupees (5)",
    "Kak 20 Gold Skulltula Reward":                         "Piece of Heart",
    "Kak 30 Gold Skulltula Reward":                         "Piece of Heart",
    "Kak 40 Gold Skulltula Reward":                         "Rupees (5)",
    "Kak 50 Gold Skulltula Reward":                         "Arrows (30)",
    "Graveyard Shield Grave Chest":                         "Recovery Heart",
    "Graveyard Heart Piece Grave Chest":                    "Rupees (20)",
    "Graveyard Royal Familys Tomb Chest":                   "Deku Stick (1)",
    "Graveyard Freestanding PoH":                           "Bombs (5)",
    "Graveyard Dampe Gravedigging Tour":                    "Rupees (50)",
    "Graveyard Dampe Race Hookshot Chest":                  "Progressive Hookshot",
    "Graveyard Dampe Race Freestanding PoH":                "Arrows (10)",
    "DMT Freestanding PoH":                                 "Boomerang",
    "DMT Chest":                                            "Rupees (50)",
    "DMT Storms Grotto Chest":                              "Rupees (5)",
    "DMT Great Fairy Reward":                               "Arrows (10)",
    "DMT Biggoron":                                         "Rupees (5)",
    "GC Darunias Joy":                                      "Slingshot",
    "GC Pot Freestanding PoH":                              "Rupees (20)",
    "GC Rolling Goron as Child":                            "Rupees (5)",
    "GC Rolling Goron as Adult":                            "Piece of Heart",
    "GC Maze Left Chest":                                   "Deku Shield",
    "GC Maze Right Chest":                                  "Piece of Heart",
    "GC Maze Center Chest":                                 "Biggoron Sword",
    "DMC Volcano Freestanding PoH":                         "Rupees (5)",
    "DMC Wall Freestanding PoH":                            "Recovery Heart",
    "DMC Upper Grotto Chest":                               "Piece of Heart",
    "DMC Great Fairy Reward":                               "Piece of Heart",
    "ZR Open Grotto Chest":                                 "Rupees (50)",
    "ZR Frogs in the Rain":                                 "Progressive Wallet",
    "ZR Frogs Ocarina Game":                                "Arrows (30)",
    "ZR Near Open Grotto Freestanding PoH":                 "Iron Boots",
    "ZR Near Domain Freestanding PoH":                      "Bomb Bag",
    "ZD Diving Minigame":                                   "Recovery Heart",
    "ZD Chest":                                             "Bottle",
    "ZD King Zora Thawed":                                  "Piece of Heart",
    "ZF Great Fairy Reward":                                "Rupees (5)",
    "ZF Iceberg Freestanding PoH":                          "Deku Seeds (30)",
    "ZF Bottom Freestanding PoH":                           "Deku Seeds (30)",
    "LH Underwater Item":                                   "Rupees (5)",
    "LH Child Fishing":                                     "Bombs (5)",
    "LH Adult Fishing":                                     "Arrows (30)",
    "LH Lab Dive":                                          "Rupees (200)",
    "LH Freestanding PoH":                                  "Stone of Agony",
    "LH Sun":                                               "Kokiri Sword",
    "GV Crate Freestanding PoH":                            "Rupees (200)",
    "GV Waterfall Freestanding PoH":                        "Deku Stick (1)",
    "GV Chest":                                             "Arrows (10)",
    "GF Chest":                                             "Bombs (20)",
    "GF HBA 1000 Points":                                   "Deku Seeds (30)",
    "GF HBA 1500 Points":                                   "Zora Tunic",
    "Wasteland Chest":                                      "Arrows (10)",
    "Colossus Great Fairy Reward":                          "Deku Nut Capacity",
    "Colossus Freestanding PoH":                            "Slingshot",
    "OGC Great Fairy Reward":                               "Piece of Heart",
    "Deku Tree Map Chest":                                  "Deku Nuts (10)",
    "Deku Tree Slingshot Room Side Chest":                  "Bottle",
    "Deku Tree Slingshot Chest":                            "Bow",
    "Deku Tree Compass Chest":                              "Bombs (5)",
    "Deku Tree Compass Room Side Chest":                    "Piece of Heart",
    "Deku Tree Basement Chest":                             "Piece of Heart",
    "Deku Tree Queen Gohma Heart":                          "Piece of Heart",
    "Dodongos Cavern Map Chest":                            "Rupees (5)",
    "Dodongos Cavern Compass Chest":                        "Rupees (50)",
    "Dodongos Cavern Bomb Flower Platform Chest":           "Piece of Heart",
    "Dodongos Cavern Bomb Bag Chest":                       "Rupees (200)",
    "Dodongos Cavern End of Bridge Chest":                  "Deku Stick Capacity",
    "Dodongos Cavern Boss Room Chest":                      "Lens of Truth",
    "Dodongos Cavern King Dodongo Heart":                   "Mirror Shield",
    "Jabu Jabus Belly Boomerang Chest":                     "Recovery Heart",
    "Jabu Jabus Belly Map Chest":                           "Progressive Strength Upgrade",
    "Jabu Jabus Belly Compass Chest":                       "Magic Meter",
    "Jabu Jabus Belly Barinade Heart":                      "Piece of Heart",
    "Bottom of the Well Front Left Fake Wall Chest":        "Rupees (50)",
    "Bottom of the Well Front Center Bombable Chest":       "Arrows (5)",
    "Bottom of the Well Back Left Bombable Chest":          "Piece of Heart",
    "Bottom of the Well Underwater Left Chest":             "Rupees (5)",
    "Bottom of the Well Freestanding Key":                  "Small Key (Bottom of the Well)",
    "Bottom of the Well Compass Chest":                     "Light Arrows",
    "Bottom of the Well Center Skulltula Chest":            "Piece of Heart",
    "Bottom of the Well Right Bottom Fake Wall Chest":      "Small Key (Bottom of the Well)",
    "Bottom of the Well Fire Keese Chest":                  "Heart Container",
    "Bottom of the Well Like Like Chest":                   "Deku Nut Capacity",
    "Bottom of the Well Map Chest":                         "Recovery Heart",
    "Bottom of the Well Underwater Front Chest":            "Bombs (5)",
    "Bottom of the Well Invisible Chest":                   "Small Key (Bottom of the Well)",
    "Bottom of the Well Lens of Truth Chest":               "Rupees (5)",
    "Forest Temple First Room Chest":                       "Small Key (Forest Temple)",
    "Forest Temple First Stalfos Chest":                    "Deku Nuts (5)",
    "Forest Temple Raised Island Courtyard Chest":          "Deku Seeds (30)",
    "Forest Temple Map Chest":                              "Small Key (Forest Temple)",
    "Forest Temple Well Chest":                             "Bow",
    "Forest Temple Eye Switch Chest":                       "Small Key (Forest Temple)",
    "Forest Temple Boss Key Chest":                         "Small Key (Forest Temple)",
    "Forest Temple Floormaster Chest":                      "Small Key (Forest Temple)",
    "Forest Temple Red Poe Chest":                          "Boss Key (Forest Temple)",
    "Forest Temple Bow Chest":                              "Rupees (5)",
    "Forest Temple Blue Poe Chest":                         "Piece of Heart",
    "Forest Temple Falling Ceiling Room Chest":             "Arrows (10)",
    "Forest Temple Basement Chest":                         "Deku Shield",
    "Forest Temple Phantom Ganon Heart":                    "Piece of Heart",
    "Fire Temple Near Boss Chest":                          "Small Key (Fire Temple)",
    "Fire Temple Flare Dancer Chest":                       "Small Key (Fire Temple)",
    "Fire Temple Boss Key Chest":                           "Small Key (Fire Temple)",
    "Fire Temple Big Lava Room Lower Open Door Chest":      "Small Key (Fire Temple)",
    "Fire Temple Big Lava Room Blocked Door Chest":         "Heart Container",
    "Fire Temple Boulder Maze Lower Chest":                 "Small Key (Fire Temple)",
    "Fire Temple Boulder Maze Side Room Chest":             "Bombchus (10)",
    "Fire Temple Map Chest":                                "Deku Stick (1)",
    "Fire Temple Boulder Maze Shortcut Chest":              "Small Key (Fire Temple)",
    "Fire Temple Boulder Maze Upper Chest":                 "Small Key (Fire Temple)",
    "Fire Temple Scarecrow Chest":                          "Small Key (Fire Temple)",
    "Fire Temple Compass Chest":                            "Hylian Shield",
    "Fire Temple Megaton Hammer Chest":                     "Rupees (5)",
    "Fire Temple Highest Goron Chest":                      "Boss Key (Fire Temple)",
    "Fire Temple Volvagia Heart":                           "Eyeball Frog",
    "Water Temple Compass Chest":                           "Small Key (Water Temple)",
    "Water Temple Map Chest":                               "Boss Key (Water Temple)",
    "Water Temple Cracked Wall Chest":                      "Small Key (Water Temple)",
    "Water Temple Torches Chest":                           "Small Key (Water Temple)",
    "Water Temple Boss Key Chest":                          "Bombs (5)",
    "Water Temple Central Pillar Chest":                    "Small Key (Water Temple)",
    "Water Temple Central Bow Target Chest":                "Small Key (Water Temple)",
    "Water Temple Longshot Chest":                          "Small Key (Water Temple)",
    "Water Temple River Chest":                             "Rupee (1)",
    "Water Temple Dragon Chest":                            "Piece of Heart",
    "Water Temple Morpha Heart":                            "Bombs (20)",
    "Shadow Temple Map Chest":                              "Small Key (Shadow Temple)",
    "Shadow Temple Hover Boots Chest":                      "Piece of Heart",
    "Shadow Temple Compass Chest":                          "Small Key (Shadow Temple)",
    "Shadow Temple Early Silver Rupee Chest":               "Piece of Heart",
    "Shadow Temple Invisible Blades Visible Chest":         "Small Key (Shadow Temple)",
    "Shadow Temple Invisible Blades Invisible Chest":       "Progressive Strength Upgrade",
    "Shadow Temple Falling Spikes Lower Chest":             "Piece of Heart",
    "Shadow Temple Falling Spikes Upper Chest":             "Deku Stick Capacity",
    "Shadow Temple Falling Spikes Switch Chest":            "Piece of Heart",
    "Shadow Temple Invisible Spikes Chest":                 "Boss Key (Shadow Temple)",
    "Shadow Temple Freestanding Key":                       "Rupees (200)",
    "Shadow Temple Wind Hint Chest":                        "Small Key (Shadow Temple)",
    "Shadow Temple After Wind Enemy Chest":                 "Progressive Scale",
    "Shadow Temple After Wind Hidden Chest":                "Bombs (10)",
    "Shadow Temple Spike Walls Left Chest":                 "Recovery Heart",
    "Shadow Temple Boss Key Chest":                         "Bombchus (10)",
    "Shadow Temple Invisible Floormaster Chest":            "Small Key (Shadow Temple)",
    "Shadow Temple Bongo Bongo Heart":                      "Bow",
    "Spirit Temple Child Bridge Chest":                     "Small Key (Spirit Temple)",
    "Spirit Temple Child Early Torches Chest":              "Small Key (Spirit Temple)",
    "Spirit Temple Child Climb North Chest":                "Small Key (Spirit Temple)",
    "Spirit Temple Child Climb East Chest":                 "Piece of Heart",
    "Spirit Temple Map Chest":                              "Heart Container",
    "Spirit Temple Sun Block Room Chest":                   "Progressive Wallet",
    "Spirit Temple Silver Gauntlets Chest":                 "Boss Key (Spirit Temple)",
    "Spirit Temple Compass Chest":                          "Arrows (5)",
    "Spirit Temple Early Adult Right Chest":                "Small Key (Spirit Temple)",
    "Spirit Temple First Mirror Left Chest":                "Small Key (Spirit Temple)",
    "Spirit Temple First Mirror Right Chest":               "Rupees (50)",
    "Spirit Temple Statue Room Northeast Chest":            "Recovery Heart",
    "Spirit Temple Statue Room Hand Chest":                 "Rupees (200)",
    "Spirit Temple Near Four Armos Chest":                  "Heart Container",
    "Spirit Temple Hallway Right Invisible Chest":          "Ice Arrows",
    "Spirit Temple Hallway Left Invisible Chest":           "Piece of Heart",
    "Spirit Temple Mirror Shield Chest":                    "Hylian Shield",
    "Spirit Temple Boss Key Chest":                         "Rupees (20)",
    "Spirit Temple Topmost Chest":                          "Piece of Heart",
    "Spirit Temple Twinrova Heart":                         "Deku Seeds (30)",
    "Ice Cavern Map Chest":                                 "Piece of Heart",
    "Ice Cavern Compass Chest":                             "Rupees (5)",
    "Ice Cavern Iron Boots Chest":                          "Rupees (5)",
    "Ice Cavern Freestanding PoH":                          "Heart Container",
    "Gerudo Training Ground Lobby Left Chest":              "Deku Seeds (30)",
    "Gerudo Training Ground Lobby Right Chest":             "Rupees (5)",
    "Gerudo Training Ground Stalfos Chest":                 "Arrows (30)",
    "Gerudo Training Ground Before Heavy Block Chest":      "Arrows (30)",
    "Gerudo Training Ground Heavy Block First Chest":       "Small Key (Gerudo Training Ground)",
    "Gerudo Training Ground Heavy Block Second Chest":      "Small Key (Gerudo Training Ground)",
    "Gerudo Training Ground Heavy Block Third Chest":       "Small Key (Gerudo Training Ground)",
    "Gerudo Training Ground Heavy Block Fourth Chest":      "Progressive Scale",
    "Gerudo Training Ground Eye Statue Chest":              "Small Key (Gerudo Training Ground)",
    "Gerudo Training Ground Near Scarecrow Chest":          "Piece of Heart",
    "Gerudo Training Ground Hammer Room Clear Chest":       "Small Key (Gerudo Training Ground)",
    "Gerudo Training Ground Hammer Room Switch Chest":      "Rupees (50)",
    "Gerudo Training Ground Freestanding Key":              "Small Key (Gerudo Training Ground)",
    "Gerudo Training Ground Maze Right Central Chest":      "Heart Container",
    "Gerudo Training Ground Maze Right Side Chest":         "Small Key (Gerudo Training Ground)",
    "Gerudo Training Ground Underwater Silver Rupee Chest": "Farores Wind",
    "Gerudo Training Ground Beamos Chest":                  "Bombchus (20)",
    "Gerudo Training Ground Hidden Ceiling Chest":          "Arrows (30)",
    "Gerudo Training Ground Maze Path First Chest":         "Small Key (Gerudo Training Ground)",
    "Gerudo Training Ground Maze Path Second Chest":        "Small Key (Gerudo Training Ground)",
    "Gerudo Training Ground Maze Path Third Chest":         "Heart Container",
    "Gerudo Training Ground Maze Path Final Chest":         "Bomb Bag",
    "Ganons Castle Forest Trial Chest":                     "Rupees (5)",
    "Ganons Castle Water Trial Left Chest":                 "Deku Seeds (30)",
    "Ganons Castle Water Trial Right Chest":                "Rupees (50)",
    "Ganons Castle Shadow Trial Front Chest":               "Heart Container",
    "Ganons Castle Shadow Trial Golden Gauntlets Chest":    "Piece of Heart (Treasure Chest Game)",
    "Ganons Castle Light Trial First Left Chest":           "Small Key (Ganons Castle)",
    "Ganons Castle Light Trial Second Left Chest":          "Magic Meter",
    "Ganons Castle Light Trial Third Left Chest":           "Bombchus (10)",
    "Ganons Castle Light Trial First Right Chest":          "Small Key (Ganons Castle)",
    "Ganons Castle Light Trial Second Right Chest":         "Nayrus Love",
    "Ganons Castle Light Trial Third Right Chest":          "Bombs (5)",
    "Ganons Castle Light Trial Invisible Enemies Chest":    "Goron Tunic",
    "Ganons Castle Light Trial Lullaby Chest":              "Arrows (10)",
    "Ganons Castle Spirit Trial Crystal Switch Chest":      "Bottle with Blue Fire",
    "Ganons Castle Spirit Trial Invisible Chest":           "Piece of Heart",
    "Ganons Tower Boss Key Chest":                          "Bombchus (5)"
  },
  ":skipped_locations":        {
    "Links Pocket":     "Fire Medallion",
    "HC Malon Egg":     "Recovery Heart",
    "HC Zeldas Letter": "Zeldas Letter",
    "Song from Impa":   "Sarias Song"
  },
  ":woth_locations":           {
    "Sheik in Forest":                      "Song of Time",
    "Graveyard Dampe Race Hookshot Chest":  "Progressive Hookshot",
    "DMT Freestanding PoH":                 "Boomerang",
    "Forest Temple Well Chest":             "Bow",
    "Kak Shooting Gallery Reward":          "Bomb Bag",
    "Market Bombchu Bowling First Prize":   "Progressive Hookshot",
    "ZR Near Open Grotto Freestanding PoH": "Iron Boots",
    "LH Sun":                               "Kokiri Sword",
    "LW Deku Scrub Grotto Front":           {"item": "Progressive Strength Upgrade", "price": 40},
    "Dodongos Cavern King Dodongo Heart":   "Mirror Shield",
    "Sheik at Temple":                      "Requiem of Spirit",
    "Sheik in Kakariko":                    "Zeldas Lullaby",
    "Sheik at Colossus":                    "Song of Storms",
    "HC Great Fairy Reward":                "Rutos Letter",
    "Jabu Jabus Belly Compass Chest":       "Magic Meter",
    "Bottom of the Well Compass Chest":     "Light Arrows"
  },
  ":goal_locations":           {
    "rainbow_bridge": {
      "Path to Phantom Ganon": {
        "Sheik in Forest":                     "Song of Time",
        "Graveyard Dampe Race Hookshot Chest": "Progressive Hookshot",
        "Forest Temple Well Chest":            "Bow",
        "Kak Shooting Gallery Reward":         "Bomb Bag",
        "LW Deku Scrub Grotto Front":          {"item": "Progressive Strength Upgrade", "price": 40}
      },
      "Path to Morpha":        {
        "Sheik in Forest":                      "Song of Time",
        "Graveyard Dampe Race Hookshot Chest":  "Progressive Hookshot",
        "Forest Temple Well Chest":             "Bow",
        "Kak Shooting Gallery Reward":          "Bomb Bag",
        "Market Bombchu Bowling First Prize":   "Progressive Hookshot",
        "ZR Near Open Grotto Freestanding PoH": "Iron Boots"
      },
      "Path to Queen Gohma":   {
        "Sheik in Forest":                     "Song of Time",
        "Graveyard Dampe Race Hookshot Chest": "Progressive Hookshot",
        "Forest Temple Well Chest":            "Bow",
        "Kak Shooting Gallery Reward":         "Bomb Bag",
        "Market Bombchu Bowling First Prize":  "Progressive Hookshot",
        "LH Sun":                              "Kokiri Sword"
      },
      "Path to King Dodongo":  {
        "Sheik in Forest":                     "Song of Time",
        "Graveyard Dampe Race Hookshot Chest": "Progressive Hookshot",
        "Forest Temple Well Chest":            "Bow",
        "Kak Shooting Gallery Reward":         "Bomb Bag"
      },
      "Path to Twinrova":      {
        "Sheik in Forest":                      "Song of Time",
        "Graveyard Dampe Race Hookshot Chest":  "Progressive Hookshot",
        "DMT Freestanding PoH":                 "Boomerang",
        "Forest Temple Well Chest":             "Bow",
        "Kak Shooting Gallery Reward":          "Bomb Bag",
        "Market Bombchu Bowling First Prize":   "Progressive Hookshot",
        "ZR Near Open Grotto Freestanding PoH": "Iron Boots",
        "LW Deku Scrub Grotto Front":           {"item": "Progressive Strength Upgrade", "price": 40},
        "Dodongos Cavern King Dodongo Heart":   "Mirror Shield",
        "Sheik at Temple":                      "Requiem of Spirit",
        "Sheik in Kakariko":                    "Zeldas Lullaby",
        "HC Great Fairy Reward":                "Rutos Letter"
      }
    }
  },
  ":barren_regions":           [
    "Gerudo Valley",
    "the Haunted Wasteland",
    "outside Ganon's Castle",
    "Zora's Fountain",
    "the Water Temple",
    "the Ice Cavern"
  ],
  "gossip_stones":             {
    "Colossus (Spirit Temple)":        {"text": "They say that #the Graveyard# is on the path to #Morpha#.", "colors": ["Blue", "Light Blue"], "hinted_locations": ["Graveyard Dampe Race Hookshot Chest"], "hinted_items": ["Progressive Hookshot"]},
    "DMC (Bombable Wall)":             {"text": "They say that the #frozen cavern# echoes with #the Serenade of Water#.", "colors": ["Green", "Red"], "hinted_locations": ["Sheik in Ice Cavern"], "hinted_items": ["Serenade of Water"]},
    "DMC (Upper Grotto)":              {"text": "They say that #the Death Mountain Trail# is on the path to #Twinrova#.", "colors": ["Yellow", "Light Blue"], "hinted_locations": ["DMT Freestanding PoH"], "hinted_items": ["Boomerang"]},
    "DMT (Biggoron)":                  {"text": "They say that slaying #40 Gold Skulltulas# reveals #a Blue Rupee#.", "colors": ["Green", "Red"], "hinted_locations": ["Kak 40 Gold Skulltula Reward"], "hinted_items": ["Rupees (5)"]},
    "DMT (Storms Grotto)":             {"text": "They say that in #Gerudo Valley# the hammer unlocks #Arrows (10 pieces)#.", "colors": ["Green", "Red"], "hinted_locations": ["GV Chest"], "hinted_items": ["Arrows (10)"]},
    "Dodongos Cavern (Bombable Wall)": {"text": "They say that the final reward from the #Frogs of Zora's River# is #Arrows (30 pieces)#.", "colors": ["Green", "Red"], "hinted_locations": ["ZR Frogs Ocarina Game"], "hinted_items": ["Arrows (30)"]},
    "GC (Maze)":                       {"text": "They say that upon the #Colossus's left hand# is #a Hylian Shield#.", "colors": ["Green", "Red"], "hinted_locations": ["Spirit Temple Mirror Shield Chest"], "hinted_items": ["Hylian Shield"]},
    "GC (Medigoron)":                  {"text": "They say that slaying #30 Gold Skulltulas# reveals #a Piece of Heart#.", "colors": ["Green", "Red"], "hinted_locations": ["Kak 30 Gold Skulltula Reward"], "hinted_items": ["Piece of Heart"]},
    "GV (Waterfall)":                  {"text": "They say that #the Forest Temple# is on the path to #King Dodongo#.", "colors": ["Red", "Light Blue"], "hinted_locations": ["Forest Temple Well Chest"], "hinted_items": ["Bow"]},
    "Graveyard (Shadow Temple)":       {"text": "They say that #Biggoron# crafts #a Blue Rupee#.", "colors": ["Green", "Red"], "hinted_locations": ["DMT Biggoron"], "hinted_items": ["Rupees (5)"]},
    "HC (Malon)":                      {"text": "They say that slaying #50 Gold Skulltulas# reveals #Arrows (30 pieces)#.", "colors": ["Green", "Red"], "hinted_locations": ["Kak 50 Gold Skulltula Reward"], "hinted_items": ["Arrows (30)"]},
    "HC (Rock Wall)":                  {"text": "They say that #Kakariko Village# is on the path to #Phantom Ganon#.", "colors": ["Green", "Light Blue"], "hinted_locations": ["Kak Shooting Gallery Reward"], "hinted_items": ["Bomb Bag"]},
    "HC (Storms Grotto)":              {"text": "They say that slaying #40 Gold Skulltulas# reveals #a Blue Rupee#.", "colors": ["Green", "Red"], "hinted_locations": ["Kak 40 Gold Skulltula Reward"], "hinted_items": ["Rupees (5)"]},
    "HF (Cow Grotto)":                 {"text": "They say that #Biggoron# crafts #a Blue Rupee#.", "colors": ["Green", "Red"], "hinted_locations": ["DMT Biggoron"], "hinted_items": ["Rupees (5)"]},
    "HF (Near Market Grotto)":         {"text": "They say that #the Death Mountain Trail# is on the path to #Twinrova#.", "colors": ["Yellow", "Light Blue"], "hinted_locations": ["DMT Freestanding PoH"], "hinted_items": ["Boomerang"]},
    "HF (Open Grotto)":                {"text": "They say that the #treasure chest game# grants #a Blue Rupee#.", "colors": ["Green", "Red"], "hinted_locations": ["Market Treasure Chest Game Reward"], "hinted_items": ["Rupees (5)"]},
    "HF (Southeast Grotto)":           {"text": "They say that upon the #Colossus's left hand# is #a Hylian Shield#.", "colors": ["Green", "Red"], "hinted_locations": ["Spirit Temple Mirror Shield Chest"], "hinted_items": ["Hylian Shield"]},
    "KF (Deku Tree Left)":             {"text": "They say that #the Sacred Forest Meadow# is on the path to #Queen Gohma#.", "colors": ["Green", "Light Blue"], "hinted_locations": ["Sheik in Forest"], "hinted_items": ["Song of Time"]},
    "KF (Deku Tree Right)":            {"text": "They say that the #treasure chest game# grants #a Blue Rupee#.", "colors": ["Green", "Red"], "hinted_locations": ["Market Treasure Chest Game Reward"], "hinted_items": ["Rupees (5)"]},
    "KF (Outside Storms)":             {"text": "They say that the #Ocarina of Time# teaches #the Prelude of Light#.", "colors": ["Green", "Red"], "hinted_locations": ["Song from Ocarina of Time"], "hinted_items": ["Prelude of Light"]},
    "KF (Storms Grotto)":              {"text": "They say that the final reward from the #Frogs of Zora's River# is #Arrows (30 pieces)#.", "colors": ["Green", "Red"], "hinted_locations": ["ZR Frogs Ocarina Game"], "hinted_items": ["Arrows (30)"]},
    "Kak (Open Grotto)":               {"text": "They say that those who seek #sunken silver rupees# will find #Farore's Wind#.", "colors": ["Green", "Red"], "hinted_locations": ["Gerudo Training Ground Underwater Silver Rupee Chest"], "hinted_items": ["Farores Wind"]},
    "LH (Lab)":                        {"text": "They say that #Kakariko Village# is on the path to #Phantom Ganon#.", "colors": ["Green", "Light Blue"], "hinted_locations": ["Kak Shooting Gallery Reward"], "hinted_items": ["Bomb Bag"]},
    "LH (Southeast Corner)":           {"text": "They say that in #Gerudo Valley# the hammer unlocks #Arrows (10 pieces)#.", "colors": ["Green", "Red"], "hinted_locations": ["GV Chest"], "hinted_items": ["Arrows (10)"]},
    "LH (Southwest Corner)":           {"text": "They say that those who seek #sunken silver rupees# will find #Farore's Wind#.", "colors": ["Green", "Red"], "hinted_locations": ["Gerudo Training Ground Underwater Silver Rupee Chest"], "hinted_items": ["Farores Wind"]},
    "LW (Bridge)":                     {"text": "They say that the #Skull Mask# yields #a Huge Rupee#.", "colors": ["Green", "Red"], "hinted_locations": ["Deku Theater Skull Mask"], "hinted_items": ["Rupees (200)"]},
    "LW (Near Shortcuts Grotto)":      {"text": "They say that #the Forest Temple# is on the path to #King Dodongo#.", "colors": ["Red", "Light Blue"], "hinted_locations": ["Forest Temple Well Chest"], "hinted_items": ["Bow"]},
    "SFM (Maze Lower)":                {"text": "They say that a #ravaged village# mourns with #Zelda's Lullaby#.", "colors": ["Green", "Red"], "hinted_locations": ["Sheik in Kakariko"], "hinted_items": ["Zeldas Lullaby"]},
    "SFM (Maze Upper)":                {"text": "They say that #Darunia's dance# leads to #a Slingshot#.", "colors": ["Green", "Red"], "hinted_locations": ["GC Darunias Joy"], "hinted_items": ["Slingshot"]},
    "SFM (Saria)":                     {"text": "They say that dodging #rolling boulders in the Water Temple# leads to #Bombs (5 pieces)#.", "colors": ["Green", "Red"], "hinted_locations": ["Water Temple Boss Key Chest"], "hinted_items": ["Bombs (5)"]},
    "ToT (Left)":                      {"text": "They say that the #frozen cavern# echoes with #the Serenade of Water#.", "colors": ["Green", "Red"], "hinted_locations": ["Sheik in Ice Cavern"], "hinted_items": ["Serenade of Water"]},
    "ToT (Left-Center)":               {"text": "They say that slaying #30 Gold Skulltulas# reveals #a Piece of Heart#.", "colors": ["Green", "Red"], "hinted_locations": ["Kak 30 Gold Skulltula Reward"], "hinted_items": ["Piece of Heart"]},
    "ToT (Right)":                     {"text": "They say that #Darunia's dance# leads to #a Slingshot#.", "colors": ["Green", "Red"], "hinted_locations": ["GC Darunias Joy"], "hinted_items": ["Slingshot"]},
    "ToT (Right-Center)":              {"text": "They say that #the Sacred Forest Meadow# is on the path to #Queen Gohma#.", "colors": ["Green", "Light Blue"], "hinted_locations": ["Sheik in Forest"], "hinted_items": ["Song of Time"]},
    "ZD (Mweep)":                      {"text": "They say that the #Skull Mask# yields #a Huge Rupee#.", "colors": ["Green", "Red"], "hinted_locations": ["Deku Theater Skull Mask"], "hinted_items": ["Rupees (200)"]},
    "ZF (Fairy)":                      {"text": "They say that the #Ocarina of Time# teaches #the Prelude of Light#.", "colors": ["Green", "Red"], "hinted_locations": ["Song from Ocarina of Time"], "hinted_items": ["Prelude of Light"]},
    "ZF (Jabu)":                       {"text": "They say that dodging #rolling boulders in the Water Temple# leads to #Bombs (5 pieces)#.", "colors": ["Green", "Red"], "hinted_locations": ["Water Temple Boss Key Chest"], "hinted_items": ["Bombs (5)"]},
    "ZR (Near Domain)":                {"text": "They say that slaying #50 Gold Skulltulas# reveals #Arrows (30 pieces)#.", "colors": ["Green", "Red"], "hinted_locations": ["Kak 50 Gold Skulltula Reward"], "hinted_items": ["Arrows (30)"]},
    "ZR (Near Grottos)":               {"text": "They say that a #ravaged village# mourns with #Zelda's Lullaby#.", "colors": ["Green", "Red"], "hinted_locations": ["Sheik in Kakariko"], "hinted_items": ["Zeldas Lullaby"]},
    "ZR (Open Grotto)":                {"text": "They say that #the Graveyard# is on the path to #Morpha#.", "colors": ["Blue", "Light Blue"], "hinted_locations": ["Graveyard Dampe Race Hookshot Chest"], "hinted_items": ["Progressive Hookshot"]}
  },
  ":playthrough":              {
    "0":  {
      "HC Zeldas Letter":                      "Zeldas Letter",
      "Links Pocket":                          "Fire Medallion",
      "Song from Impa":                        "Sarias Song"
    },
    "1":  {
      "DMT Freestanding PoH":                  "Boomerang",
      "Graveyard Dampe Race Hookshot Chest":   "Progressive Hookshot",
      "KF Midos Top Right Chest":              "Slingshot",
      "KF Shop Item 1":                        "Buy Deku Shield",
      "Kak Bazaar Item 7":                     "Buy Deku Stick (1)",
      "Master Sword Pedestal":                 "Time Travel",
      "Sheik in Forest":                       "Song of Time"
    },
    "2":  {
      "Forest Temple First Room Chest":        "Small Key (Forest Temple)",
      "Forest Temple Map Chest":               "Small Key (Forest Temple)",
      "Forest Temple Well Chest":              "Bow",
      "Pierre":                                "Scarecrow Song"
    },
    "3":  {
      "Kak Shooting Gallery Reward":           "Bomb Bag"
    },
    "4":  {
      "Dodongos Cavern King Dodongo Heart":    "Mirror Shield",
      "King Dodongo":                          "Spirit Medallion",
      "LW Deku Scrub Grotto Front":            "Progressive Strength Upgrade",
      "Market Bombchu Bowling First Prize":    "Progressive Hookshot",
      "ZR Near Open Grotto Freestanding PoH":  "Iron Boots"
    },
    "5":  {
      "Forest Temple Boss Key Chest":          "Small Key (Forest Temple)",
      "Forest Temple Eye Switch Chest":        "Small Key (Forest Temple)",
      "Forest Temple Floormaster Chest":       "Small Key (Forest Temple)",
      "LH Sun":                                "Kokiri Sword",
      "Water Temple Map Chest":                "Boss Key (Water Temple)"
    },
    "6":  {
      "Forest Temple Red Poe Chest":           "Boss Key (Forest Temple)",
      "Morpha":                                "Water Medallion",
      "Queen Gohma":                           "Shadow Medallion"
    },
    "7":  {
      "Phantom Ganon":                         "Forest Medallion"
    },
    "8":  {
      "Sheik at Temple":                       "Requiem of Spirit",
      "Sheik in Kakariko":                     "Zeldas Lullaby"
    },
    "9":  {
      "HC Great Fairy Reward":                 "Rutos Letter",
      "Sheik at Colossus":                     "Song of Storms",
      "Spirit Temple Child Bridge Chest":      "Small Key (Spirit Temple)",
      "Spirit Temple Child Early Torches Chest":"Small Key (Spirit Temple)"
    },
    "10": {
      "Bottom of the Well Compass Chest":      "Light Arrows",
      "Deliver Rutos Letter":                  "Deliver Letter",
      "Spirit Temple Child Climb North Chest": "Small Key (Spirit Temple)"
    },
    "11": {
      "Spirit Temple Silver Gauntlets Chest":  "Boss Key (Spirit Temple)",
      "ZR Open Grotto Lone Fish":              "Fish"
    },
    "12": {
      "Jabu Jabus Belly Compass Chest":        "Magic Meter",
      "Jabu Jabus Belly Map Chest":            "Progressive Strength Upgrade"
    },
    "13": {
      "Spirit Temple Early Adult Right Chest": "Small Key (Spirit Temple)",
      "Spirit Temple First Mirror Left Chest": "Small Key (Spirit Temple)"
    },
    "14": {
      "Twinrova":                              "Light Medallion"
    },
    "15": {
      "Ganon":                                 "Triforce"
    }
  },
  ":entrance_playthrough":     {
    "2": {
      "Child Spawn -> KF Links House":{"region": "Lost Woods", "from": "Kokiri Forest"}
    }
  }
}